Workbook

Sheet 目标管理
A1: 专项名称 | B1: 专项负责人 | C1: 子专项 | D1: 子专项责任人 | E1: 目标名称 | F1: 计算方式/说明 | G1: 数据来源 | H1: 数据口径是否明确 | I1: 数据获取时间 | J1: 是否量化 | K1: 是否自动化 | L1: 基线值 | M1: 年度目标值 | N1: 3月（目标） | O1: 4月（目标） | P1: 5月（目标） | Q1: 6月（目标） | R1: 7月（目标） | S1: 8月（目标） | T1: 9月（目标） | U1: 10月（目标） | V1: 11月（目标） | W1: 12月（目标）
A2: MTPF提升专项 | B2: 徐融 | C2: / | D2: 徐融 | E2: SWGT MTPF平均故障间隔时间（小时） | F2: MTPF = 设备运行总时长/运维介入售后工单数 基线数据：Q1作为基线 目标值：12月31日≥400h 年度目标进度：实际值/目标值 | G2: 数字中台 （季明清） | H2: 定义清晰 | I2: 次月1日内 | J2: 是 | K2: 是 | L2: 1.83 | M2: 400 | N2: 5 | O2: 10 | P2: 20 | Q2: 30 | R2: 50 | S2: 100 | T2: 150 | U2: 200 | V2: 300 | W2: 400
A3: MTPF提升专项 | B3: 徐融 | C3: / | D3: 徐融 | E3: SW50 MTPF平均故障间隔时间（小时） | F3: MTPF = 设备运行总时长/运维介入售后工单数 基线数据：Q1作为基线 目标值：12月31日≥400h 年度目标进度：实际值/目标值 | G3: 数字中台 （季明清） | H3: 定义清晰 | I3: 次月1日内 | J3: 是 | K3: 是 | L3: 1.88 | M3: 400 | N3: 5 | O3: 10 | P3: 20 | Q3: 30 | R3: 50 | S3: 100 | T3: 150 | U3: 200 | V3: 300 | W3: 400
A4: MTPF提升专项 | B4: 徐融 | C4: / | D4: 徐融 | E4: Titan810 MTPF平均故障间隔时间（小时） | F4: MTPF = 设备运行总时长/运维介入售后工单数 基线数据：Q1作为基线 目标值：12月31日≥400h 年度目标进度：实际值/目标值 | G4: 数字中台 （季明清） | H4: 定义清晰 | I4: 次月1日内 | J4: 是 | K4: 是 | L4: 6.37 | M4: 400 | N4: 5 | O4: 10 | P4: 20 | Q4: 30 | R4: 50 | S4: 100 | T4: 150 | U4: 200 | V4: 300 | W4: 400
A5: MTPF提升专项 | B5: 徐融 | C5: / | D5: 徐融 | E5: SWGT "1460"指标（小时） | F5: 1460 = 设备运行总时长/（软件自恢复失败次数+硬件维修次数） 基线数据： 目标值：12月31日≥2000h 年度目标进度：实际值/目标值 | G5: 数字中台 （季明清） 维修单 （郭轶） 袁德明核算 | H5: 定义清晰 | I5: 次月1日内 | J5: 是 | K5: 待定 | L5: / | M5: 2000 | N5: 570 | O5: 650 | P5: 750 | Q5: 860 | R5: 990 | S5: 1150 | T5: 1300 | U5: 1500 | V5: 1740 | W5: 2000
A6: MTPF提升专项 | B6: 徐融 | C6: / | D6: 徐融 | E6: SW50 "1460"指标（小时） | F6: 1460 = 设备运行总时长/（软件自恢复失败次数+硬件维修次数） 基线数据： 目标值：12月31日≥2000h 年度目标进度：实际值/目标值 | G6: 数字中台 （季明清） 维修单 （郭轶） 袁德明核算 | H6: 定义清晰 | I6: 次月1日内 | J6: 是 | K6: 待定 | L6: / | M6: 2000 | N6: 570 | O6: 650 | P6: 750 | Q6: 860 | R6: 990 | S6: 1150 | T6: 1300 | U6: 1500 | V6: 1740 | W6: 2000
A7: MTPF提升专项 | B7: 徐融 | C7: / | D7: 徐融 | E7: Titan810 "1460"指标（小时） | F7: 1460 = 设备运行总时长/（软件自恢复失败次数+硬件维修次数） 基线数据： 目标值：12月31日≥2000h 年度目标进度：实际值/目标值 | G7: 数字中台 （季明清） 维修单 （郭轶） 袁德明核算 | H7: 定义清晰 | I7: 次月1日内 | J7: 是 | K7: 待定 | L7: / | M7: 2000 | N7: 570 | O7: 650 | P7: 750 | Q7: 860 | R7: 990 | S7: 1150 | T7: 1300 | U7: 1500 | V7: 1740 | W7: 2000
A8: 8H部署专项 | B8: 崔凯旋 | C8: / | D8: 崔凯旋 | E8: SWGT 部署时长（小时） | F8: 从进场到完成部署的总耗时（小时） 基线数据：2025年全年平均值 目标值：8月31日前实现SW GT 8小时内完成机器部署 目标进度：目标值/实际值 | G8: 数字中台 （郭轶） | H8: 定义清晰 | I8: 次月1日内 | J8: 是 | K8: 是 | L8: 39.2 | M8: 8 | N8: 27 | O8: 22 | P8: 19 | Q8: 17 | R8: 11 | S8: 8 | T8: 8 | U8: 8 | V8: 8 | W8: 8
A9: 8H部署专项 | B9: 崔凯旋 | C9: / | D9: 崔凯旋 | E9: Titan810 部署时长（小时） | F9: 从进场到完成部署的总耗时（小时） 基线数据：2025年全年平均值 目标值：12月31日前实现Titan 810 8小时内完成机器部署 目标进度：目标值/实际值 | G9: 数字中台 （郭轶） | H9: 定义清晰 | I9: 次月1日内 | J9: 是 | K9: 是 | L9: 74.7 | M9: 8 | N9: 50 | O9: 50 | P9: 45 | Q9: 41 | R9: 32 | S9: 26 | T9: 21 | U9: 17 | V9: 14 | W9: 8
A10: 数字中台专项 | B10: 季明清 | C10: / | D10: 季明清 | E10: MES上线 | F10: 非量化指标，以系统上线（100%）节点为准 基线数据：不涉及 目标值：4月底前完成MES上线 月度完成率：上线：100%、未上线：无风险70%、有风险：40%；每提前一天+2% 目标进度：30%+30%+40% | G10: 评审报告 （公司级-季明清） | H10: 定义清晰 | I10: 次月1日内 | J10: 否 | K10: / | L10: 非量化指标 不涉及 | M10: 4月底前完成MES上线 | N10: — | O10: MES上线 | P10: — | Q10: — | R10: — | T10: — | U10: — | V10: — | W10: —
A11: 数字中台专项 | B11: 季明清 | C11: / | D11: 季明清 | E11: 三流合一 | F11: 非量化指标，以系统上线（100%）节点为准 基线数据：不涉及 目标值：6月底前支撑财务和供应链管理 月度完成率：上线：100%、未上线：无风险70%、有风险：40%；每提前一天+2% 目标进度：30%+30%+40% | G11: 评审报告 （公司级-季明清） | H11: 定义清晰 | I11: 次月1日内 | J11: 否 | K11: / | L11: 非量化指标 不涉及 | M11: 6月底前支撑财务和供应链管理 | N11: — | O11: — | P11: — | Q11: 财务及供应链管理上线 | R11: — | S11: — | T11: — | U11: — | V11: — | W11: —
A12: 数字中台专项 | B12: 季明清 | C12: / | D12: 季明清 | E12: 0号员工上线 | F12: 非量化指标，以系统上线（100%）节点为准 基线数据：不涉及 目标值：8月底前完成0号员工上线 月度完成率：上线：100%、未上线：无风险70%、有风险：40%；每提前一天+2% 目标进度：30%+30%+40% | G12: 评审报告 （公司级-季明清） | H12: 定义清晰 | I12: 次月1日内 | J12: 否 | K12: / | L12: 非量化指标 不涉及 | M12: 8月底前完成0号员工上线 | N12: — | O12: — | P12: — | Q12: — | R12: — | S12: 0号员工上线（8月底） | T12: — | U12: — | V12: — | W12: —
A13: 质量提升专项 | B13: 吴赛 | C13: 合同质量 | D13: 张海滨 | E13: 合同质量-异常率 | F13: 合同异常率=异常合同数/签约合同总数（定义不清楚） 基线数据：不涉及 目标值：合同异常率≤5% 目标进度：目标值/实际值 | G13: 徐萍提供 合同变更 销售管理办公室 | H13: 定义不明确 | J13: 是 | K13: 否 | N13: ≤5% | O13: ≤5% | P13: ≤5% | Q13: ≤5% | R13: ≤5% | S13: ≤5% | T13: ≤5% | U13: ≤5% | V13: ≤5% | W13: ≤5%
A14: 质量提升专项 | B14: 吴赛 | C14: 合同质量 | D14: 张海滨 | E14: 合同质量-非正常优惠率 | F14: 非正常优惠率=非正常优惠合同金额/合同总额（定义不清楚） 基线数据：不涉及 目标值：非正常优惠合同比例≤10% 目标进度：目标值/实际值 | G14: 张海滨+徐萍 销售管理办公室 | H14: 定义不明确 | J14: 是 | K14: 否 | N14: ≤10% | O14: ≤10% | P14: ≤10% | Q14: ≤10% | R14: ≤10% | S14: ≤10% | T14: ≤10% | U14: ≤10% | V14: ≤10% | W14: ≤10%
A15: 质量提升专项 | B15: 吴赛 | C15: 研发质量 | D15: 袁德明 | E15: 研发质量-SWGT测试泄漏率 | F15: 测试泄漏率 = 现场问题总数 / (测试故障数+生产问题数+现场问题数)--不包含重复问题、非问题 基线数据：高于底线值40%不得分 目标值：截至12月31日所有数据 目标进度：（底线值-实际值）/(底线值-目标值) | G15: JIRA 袁德明核算 | H15: 定义清晰 | I15: 次月1日内 | J15: 是 | K15: 是 | L15: 0.4 | M15: 0.1 | N15: 0.3 | O15: 0.25 | P15: 0.25 | Q15: 0.2 | R15: 0.2 | S15: 0.2 | T15: 0.15 | U15: 0.15 | V15: 0.15 | W15: 0.1
A16: 质量提升专项 | B16: 吴赛 | C16: 研发质量 | D16: 袁德明 | E16: 研发质量-Titan810测试泄漏率 | F16: 测试泄漏率 = 现场问题总数 / (测试故障数+生产问题数+现场问题数)--不包含重复问题、非问题 基线数据：高于底线值40%不得分 目标值：2025年开始截至2026年12月所有数据 目标进度：（底线值-实际值）/(底线值-目标值) | G16: JIRA 袁德明核算 | I16: 次月1日内 | J16: 是 | K16: 是 | L16: 0.4 | M16: 0.1 | N16: 0.3 | O16: 0.25 | P16: 0.25 | Q16: 0.2 | R16: 0.2 | S16: 0.2 | T16: 0.15 | U16: 0.15 | V16: 0.15 | W16: 0.1
A17: 质量提升专项 | B17: 吴赛 | C17: 研发质量 | D17: 袁德明 | E17: 研发质量-JIRA及时关闭率 | F17: JIRA现场问题/测试故障/生产问题中，30天内已关闭数/总数--历史解决+新增30天解决 基线数据：2026年Q1数据 目标值：2026年Q4数据 目标进度：（实际值-基线值）/(目标值-基线值) | G17: JIRA 袁德明核算 | H17: 定义清晰 | I17: 次月1日内 | J17: 是 | K17: 是 | L17: 0.4109 | M17: 0.9 | N17: 0.6 | O17: 0.7 | P17: 0.75 | Q17: 0.8 | R17: 0.8 | S17: 0.8 | T17: 0.85 | U17: 0.85 | V17: 0.85 | W17: 0.9
A18: 质量提升专项 | B18: 吴赛 | C18: 采购质量 | D18: 巴路瑶 | E18: 采购质量-来料批次不良 | F18: 每月来料检验中不良批次数量 基线数据：暂无 目标值：0 目标进度：按当月有无，判定0或100% | G18: 供应链提供 质量审核 （巴路瑶） | H18: 定义清晰 | I18: 次月1日内 | J18: 是 | K18: 否 | L18: 暂无 | M18: 来料批次不良0次 | N18: 0次 | O18: 0次 | P18: 0次 | Q18: 0次 | R18: 0次 | S18: 0次 | T18: 0次 | U18: 0次 | V18: 0次 | W18: 0次
A19: 质量提升专项 | B19: 吴赛 | C19: 生产质量 | D19: 吴赛 | E19: 生产过程质量-SWGT 开箱合格率 | F19: 开箱合格率 = 开箱合格台数/总出货台数 基线数据：2025年全年80.6% 目标值：开箱合格率≥98%（10-12月） 目标进度：（实际值-基线值）/(目标值-基线值) | G19: 质量统计 （吴赛） | H19: 定义清晰 | I19: 次月1日内 | J19: 是 | K19: 否 | L19: 0.806 | M19: 0.98 | N19: 0.85 | O19: 0.85 | P19: 0.85 | Q19: 0.85 | R19: 0.9 | S19: 0.9 | T19: 0.9 | U19: 0.98 | V19: 0.98 | W19: 0.98
A20: 质量提升专项 | B20: 吴赛 | C20: 生产质量 | D20: 吴赛 | E20: 生产过程质量-SW50 开箱合格率 | F20: 开箱合格率 = 开箱合格台数/总出货台数 基线数据：2025年全年80.42% 目标值：开箱合格率≥98%（10-12月） 目标进度：（实际值-基线值）/(目标值-基线值) | G20: 质量统计 （吴赛） | H20: 定义清晰 | I20: 次月1日内 | J20: 是 | K20: 否 | L20: 0.8042 | M20: 0.98 | N20: 0.85 | O20: 0.85 | P20: 0.85 | Q20: 0.85 | R20: 0.9 | S20: 0.9 | T20: 0.9 | U20: 0.98 | V20: 0.98 | W20: 0.98
A21: 质量提升专项 | B21: 吴赛 | C21: 生产质量 | D21: 吴赛 | E21: 生产过程质量-Titan810 开箱合格率 | F21: 开箱合格率 = 开箱合格台数/总出货台数 基线数据：2025年全年75% 目标值：开箱合格率≥98%（10-12月） 目标进度：（实际值-基线值）/(目标值-基线值) | G21: 质量统计 （吴赛） | H21: 定义清晰 | I21: 次月1日内 | J21: 是 | K21: 否 | L21: 0.75 | M21: 0.98 | N21: 0.85 | O21: 0.85 | P21: 0.85 | Q21: 0.85 | R21: 0.9 | S21: 0.9 | T21: 0.9 | U21: 0.98 | V21: 0.98 | W21: 0.98
A22: 质量提升专项 | B22: 吴赛 | C22: 生产质量 | D22: 吴赛 | E22: 生产过程质量-SWGT 90天内维修率 | F22: 90天内维修率 = 90天内发生维修的台数/总出货台数 基线数据：无 目标值：90天内维修率≤3%（10-12月） 目标进度：目标值/实际值 | G22: 质量统计 （吴赛） | H22: 定义清晰 | I22: 次月1日内 | J22: 是 | K22: 否 | L22: / | M22: 0.03 | N22: 0.07 | O22: 0.07 | P22: 0.07 | Q22: 0.07 | R22: 0.05 | S22: 0.05 | T22: 0.05 | U22: 0.03 | V22: 0.03 | W22: 0.03
A23: 质量提升专项 | B23: 吴赛 | C23: 生产质量 | D23: 吴赛 | E23: 生产过程质量-SW50 90天内维修率 | F23: 90天内维修率 = 90天内发生维修的台数/总出货台数 基线数据：无 目标值：90天内维修率≤3%（10-12月） 目标进度：目标值/实际值 | G23: 质量统计 （吴赛） | H23: 定义清晰 | I23: 次月1日内 | J23: 是 | K23: 否 | L23: / | M23: 0.03 | N23: 0.07 | O23: 0.07 | P23: 0.07 | Q23: 0.07 | R23: 0.05 | S23: 0.05 | T23: 0.05 | U23: 0.03 | V23: 0.03 | W23: 0.03
A24: 质量提升专项 | B24: 吴赛 | C24: 生产质量 | D24: 吴赛 | E24: 生产过程质量-Titan810 90天内维修率 | F24: 90天内维修率 = 90天内发生维修的台数/总出货台数 基线数据：无 目标值：90天内维修率≤3%（10-12月） 目标进度：目标值/实际值 | G24: 质量统计 （吴赛） | H24: 定义清晰 | I24: 次月1日内 | J24: 是 | K24: 否 | L24: / | M24: 0.03 | N24: 0.07 | O24: 0.07 | P24: 0.07 | Q24: 0.07 | R24: 0.05 | S24: 0.05 | T24: 0.05 | U24: 0.03 | V24: 0.03 | W24: 0.03
A25: 质量提升专项 | B25: 吴赛 | C25: 售后质量 | D25: 崔凯旋 | E25: 售后质量-问题一次性解决率 | F25: 售后问题一次解决数/解决总数 在系统未上线之前，数字中台中的售后维修流程统计（通过一台机器90天内的重复维修计算） 基线数据：待补充 目标值：≥95% 目标进度：实际值/目标值 | G25: 6月前手工 6月后系统 （郭轶） | H25: 定义不明确 | J25: 是 | K25: 否 | L25: 需要基线值计算进度和月度目标达成率 | M25: 0.95 | N25: 0.85 | O25: 0.85 | P25: 0.85 | Q25: 0.85 | R25: 0.9 | S25: 0.9 | T25: 0.9 | U25: 0.9 | V25: 0.95 | W25: 0.95
A26: 质量提升专项 | B26: 吴赛 | C26: 售后质量 | D26: 崔凯旋 | E26: 售后质量-平均解决时效（一线城市）（小时） | F26: 售后问题从提出到解决时间 在系统未上线之前，以维修工单的起止时间计算 基线数据：暂无 目标值：≤48H 目标进度：（基线值-实际值）/(基线值-目标值) | G26: 6月前手工 6月后系统 （郭轶） | H26: 定义不明确 | J26: 是 | K26: 否 | L26: 需要基线值计算进度和月度目标达成率 | M26: 48 | N26: 72H | O26: 72H | P26: 72H | Q26: 72H | R26: 48H | S26: 48H | T26: 48H | U26: 48H | V26: 48H | W26: 48H
A27: 质量提升专项 | B27: 吴赛 | C27: 售后质量 | D27: 崔凯旋 | E27: 售后质量-平均解决时效（二线城市）（小时） | F27: 售后问题从提出到解决时间 在系统未上线之前，以维修工单的起止时间计算 基线数据：暂无 目标值：≤72H 目标进度：（基线值-实际值）/(基线值-目标值) | G27: 6月前手工 6月后系统 （郭轶） | H27: 定义不明确 | J27: 是 | K27: 否 | L27: 需要基线值计算进度和月度目标达成率 | M27: 72 | N27: 120H | O27: 120H | P27: 120H | Q27: 120H | R27: 96H | S27: 96H | T27: 96H | U27: 96H | V27: 72H | W27: 72H
A28: 质量提升专项 | B28: 吴赛 | C28: 售后质量 | D28: 崔凯旋 | E28: 售后质量-平均解决时效（海外核心国家）（小时） | F28: 售后问题从提出到解决时间 在系统未上线之前，以维修工单的起止时间计算 基线数据：暂无 目标值：≤48H 目标进度：（基线值-实际值）/(基线值-目标值) | G28: 6月前手工 6月后系统 （郭轶） | H28: 定义不明确 | J28: 是 | K28: 否 | L28: 需要基线值计算进度和月度目标达成率 | M28: 48 | N28: 120H | O28: 120H | P28: 120H | Q28: 120H | R28: 72H | S28: 72H | T28: 72H | U28: 72H | V28: 48H | W28: 48H
A29: 质量提升专项 | B29: 吴赛 | C29: 售后质量 | D29: 崔凯旋 | E29: 售后质量-平均解决时效（海外其他国家）（小时） | F29: 售后问题从提出到解决时间 在系统未上线之前，以维修工单的起止时间计算 基线数据：暂无 目标值：≤72H 目标进度：（基线值-实际值）/(基线值-目标值) | G29: 6月前手工 6月后系统 （郭轶） | H29: 定义不明确 | J29: 是 | K29: 否 | L29: 需要基线值计算进度和月度目标达成率 | M29: 72 | N29: 120H | O29: 120H | P29: 120H | Q29: 120H | R29: 96H | S29: 96H | T29: 96H | U29: 96H | V29: 72H | W29: 72H
A30: 渠道管理能力提升 | B30: 张海滨 | C30: 经销商收入 | D30: 张海滨 | E30: 经销商收入（累计） | F30: 各月经销商实际签约/交付收入累计额 基线数据：暂无 目标值：12月经销商累计收入1.6亿元 目标进度：实际值/目标值 | G30: 财务提供总数合同签约明细，运营拆分 袁子清 徐萍 | H30: 定义清晰 | I30: 上线前：次月18日内 | J30: 是 | K30: 否 | N30: 1500万 | O30: 2000万 | P30: 2800万 | Q30: 4600万 | R30: 6000万 | S30: 8000万 | T30: 9000万 | U30: 1.2亿 | V30: 1.4亿 | W30: 1.6亿
A31: 渠道管理能力提升 | B31: 张海滨 | C31: 经销商收入 | D31: 张海滨 | E31: 新增经销商数量（月新增） | F31: 每月新签合作协议的经销商数量 基线数据：暂无 目标值：每月新增经销商3个， 月度按3个去算，半年度和年度可以累积计算 目标进度：实际值/目标值 | G31: 渠道管理部提供 张海滨 | H31: 定义清晰 | J31: 是 | K31: 否 | N31: 新增3个 | O31: 新增3个 | P31: 新增3个 | Q31: 新增3个 | R31: 新增3个 | S31: 新增3个 | T31: 新增3个 | U31: 新增3个 | V31: 新增3个 | W31: 新增3个
A32: 渠道管理能力提升 | B32: 张海滨 | C32: 经销商收入 | D32: 张海滨 | E32: 经销商存销比 | F32: 存销比 = 经销商库存 / 月销量（暂定，崔老师提供） 基线数据：暂无 目标值：Q3起存销比≤1.5:1 目标进度：目标值/实际值 | G32: 财务提供 崔凯旋 | H32: 定义不明确 | J32: 是 | K32: 否 | N32: 2:1 | O32: 2:1 | P32: 2:1 | Q32: 1.5:1 | R32: 1.5:1 | S32: 1.5:1 | T32: 1.5:1 | U32: 1.5:1 | V32: 1.5:1 | W32: 1.5:1
A33: 渠道管理能力提升 | B33: 张海滨 | C33: 经销商收入 | D33: 张海滨 | E33: 经销商复购率 | F33: 复购率 = 有复购行为的经销商数 / 存量经销商总数 基线数据：暂无 目标值：12月经销商复购率达70% 目标进度：实际值/目标值 | G33: 财务提供 徐萍提供 | H33: 定义清晰 | J33: 是 | K33: 否 | N33: 0.1 | O33: 0.15 | P33: 0.25 | Q33: 0.35 | R33: 0.45 | S33: 0.55 | T33: 0.6 | U33: 0.65 | V33: 0.7 | W33: 70%
A34: 渠道管理能力提升 | B34: 崔凯旋 | C34: 经销商服务收费 | D34: 崔凯旋 | E34: 国际累计收费服务经销商占比 | F34: 基线数据：暂无 目标值：国内国际累计收费服务经销商比例占比超过35% 目标进度：实际值/目标值 | G34: 运营管理部提供 崔老师 徐萍提供 | H34: 定义清晰 | J34: 是 | K34: 否 | N34: / | O34: / | P34: / | Q34: 6月，完成经销商服务收费合同模板修订并进行发布 | R34: 7月，新签国际经销商POC服务收费 | S34: / | T34: 0.3 | U34: 0.4 | V34: 0.5 | W34: 累积35%
A35: 渠道管理能力提升 | B35: 崔凯旋 | C35: 经销商服务收费 | D35: 崔凯旋 | E35: 国内累计收费服务经销商占比 | F35: 基线数据：暂无 目标值：国内国际累计收费服务经销商比例占比超过35% 目标进度：实际值/目标值 | G35: 运营管理部提供 崔老师 徐萍提供 | H35: 定义清晰 | J35: 是 | K35: 否 | N35: / | O35: / | P35: / | Q35: 6月，完成经销商服务收费合同模板修订并进行发布 | R35: / | S35: 8月MTPF达到100小时，GT达到8小时部署后，所有国内新签经销商POC服务收费 | T35: 0.1 | U35: 0.15 | V35: 0.25 | W35: 累积35%
A36: Marketing能力提升 | B36: 张海滨 | C36: / | D36: 张海滨 | E36: 毛利率 | F36: 毛利率 = (收入 - 成本) / 收入 基线数据：暂无 目标值：12月毛利率达60% 目标进度：实际值/目标值（负数为0） | G36: 财务数据 袁子清 | H36: 定义清晰 | I36: 次月18日提供 | J36: 是 | K36: 否 | N36: 0.3 | O36: 0.35 | P36: 0.37 | Q36: 0.4 | R36: 0.45 | S36: 0.45 | T36: 0.5 | U36: 0.52 | V36: 0.56 | W36: 0.6
A37: Marketing能力提升 | B37: 张海滨 | C37: / | D37: 张海滨 | E37: 应收周转天数 | F37: 应收账款转化为现金的等待时间 基线数据：不涉及 目标值：12月应收周转天数≤40天 月度完成率： 目标进度：目标值/实际值 | G37: 财务数据 袁子清 | H37: 定义清晰 | I37: 次月18日提供 | J37: 是 | K37: 否 | N37: 98天 | O37: 60天 | P37: 56天 | Q37: 55天 | R37: 50天 | S37: 48天 | T37: 46天 | U37: 45天 | V37: 42天 | W37: 40天
A38: 政府资金专项 | B38: 何波 | C38: / | D38: 何波 | E38: 政府资金到账额（万元） | F38: 实际到账/减免金额累计 基线数据：0 目标值：到账1750万元（含减免费用）南京1000万，嘉兴750万 目标进度：实际值/目标值 | G38: 财务确认 袁子清 | H38: 定义清晰 | J38: 是 | K38: 否 | L38: 0 | M38: 1750 | N38: 到账300万 | O38: C17栋房租减免155万+红枫科技园减免432万 | P38: 到账150万 | Q38: — | R38: — | S38: 红枫科技园装修款到账500万 | T38: — | U38: 申报省级双创团队 | V38: — | W38: 嘉兴南湖750万到账 80万元到账；500万元获批；
A39: 政府资金专项 | B39: 何波 | C39: / | D39: 何波 | E39: 新增政府资金获批（万元） | F39: 累计政府获批资金（补贴或减免） 基线数据：0 目标值：新增3000万获批，南京500万，嘉兴1500万，深圳1000万 目标进度：实际值/目标值 | G39: 政府批示文件 何波举证 | H39: 定义清晰 | J39: 是 | K39: 否 | L39: 0 | M39: 3000 | N39: — | O39: — | P39: 嘉兴项目公司注册，人才项目申请 | Q39: 深圳落地公司注册 | R39: 申请设备投资补助300万元 节约租金约45万元 | S39: — | T39: — | U39: — | V39: 获批1000万元 获批1345万元 | W39: 南京政府资金，500万元获批；
A40: 降本专项 | B40: 巴路瑶 | C40: 非独家占比 | D40: 陈栋力 | E40: GT非独家物料占比 | F40: GT非独家物料金额 / GT物料总额 基线数据：以2026年2月为基线 目标值：6月底GT非独家占比达到85% 目标进度：实际值/目标值 | G40: 质量统计 以BOM为准 陈栋力 | H40: 定义清晰 | I40: 次月1日内 | J40: 是 | K40: 否 | L40: 0.12 | M40: 0.85 | N40: 0.3 | O40: 0.45 | P40: 0.6 | Q40: 0.85 | R40: — | S40: — | T40: — | U40: — | V40: — | W40: —
A41: 降本专项 | B41: 巴路瑶 | C41: 非独家占比 | D41: 陈栋力 | E41: T810非独家物料占比 | F41: T810非独家物料金额 / T810物料总额 基线数据：以2026年2月为基线 目标值：6月底T810非独家占比达到65% 目标进度：实际值/目标值 | G41: 质量统计 以BOM为准 陈栋力 | H41: 定义清晰 | I41: 次月1日内 | J41: 是 | K41: 否 | L41: 0.23 | M41: 0.65 | N41: 0.25 | O41: 0.4 | P41: 0.5 | Q41: 0.65 | R41: — | S41: — | T41: — | U41: — | V41: — | W41: —
A42: 降本专项 | B42: 巴路瑶 | C42: 降本 | D42: 巴路瑶 | E42: GT BOM成本降低（元） | F42: 采购成本降低额（含税，相对基准BOM） 基线数据：以2025年12月为基线 目标值：10000元（含税），6月前采购额，7月后发货额 目标进度：实际值/目标值 | G42: 生产提供（巴路瑶），财务核实（袁子清） | H42: 定义清晰 | I42: 次月1日内 | J42: 是 | K42: 否 | L42: 0 | M42: 10000 | N42: 1454 | O42: 1454 | P42: 8800.56 | Q42: 10180.33 | R42: 10000 | S42: 10000 | T42: 10000 | U42: 10000 | V42: 10000 | W42: 10000
A43: 降本专项 | B43: 巴路瑶 | C43: 降本 | D43: 巴路瑶 | E43: GT包装成本降低（元） | F43: 包装成本降低额（元/套），相对现有包装成本 基线数据：以2025年12月为基线 目标值：330元，6月前采购额，7月后发货额 目标进度：实际值/目标值 | G43: 生产提供（巴路瑶），财务核实（袁子清） | H43: 定义清晰 | I43: 次月1日内 | J43: 是 | K43: 否 | L43: 0 | M43: 330 | N43: 330 | O43: 330 | P43: 330 | Q43: 330 | R43: 330 | S43: 330 | T43: 330 | U43: 330 | V43: 330 | W43: 330
A44: 降本专项 | B44: 巴路瑶 | C44: 降本 | D44: 巴路瑶 | E44: 810 BOM成本降低（元） | F44: 采购成本降低额（含税，相对基准BOM） 基线数据：以2025年12月为基线 目标值：30000元（含税），6月前采购额，7月后发货额 目标进度：实际值/目标值 | G44: 生产提供（巴路瑶），财务核实（袁子清） | H44: 定义清晰 | I44: 次月1日内 | J44: 是 | K44: 否 | L44: 0 | M44: 30000 | N44: 1351 | O44: 1351 | P44: 6773 | Q44: 30694 | R44: 30000 | S44: 30000 | T44: 30000 | U44: 30000 | V44: 30000 | W44: 30000
A45: 降本专项 | B45: 巴路瑶 | C45: 降本 | D45: 巴路瑶 | E45: 810包装成本降低（元） | F45: 包装成本降低额（元/套），相对现有包装成本 基线数据：以2025年12月为基线 目标值：707元，6月前采购额，7月后发货额 目标进度：实际值/目标值 | G45: 生产提供（巴路瑶），财务核实（袁子清） | H45: 定义清晰 | I45: 次月1日内 | J45: 是 | K45: 否 | L45: 0 | M45: 707 | N45: 707 | O45: 707 | P45: 707 | Q45: 707 | R45: 707 | S45: 707 | T45: 707 | U45: 707 | V45: 707 | W45: 707
A46: 生产提效降费专项 | B46: 夏文昊 | C46: / | D46: 夏文昊 | E46: 全年生产成本占比 | F46: 生产成本（人工/固定资产折旧/水电）/发货成本 基线数据：以2025年度为基线（不包括水电费） 目标值：全年生产成本占比不高于6% 目标进度：目标值/实际值 | G46: 财务数据 （袁子清） | H46: 定义清晰 | I46: 次月18日提供 | J46: 是 | K46: 否 | L46: 0.1224 | M46: 0.06 | N46: 0.1 | O46: 0.08 | P46: 0.08 | Q46: 0.08 | R46: 0.07 | S46: 0.07 | T46: 0.07 | U46: 0.06 | V46: 0.06 | W46: 0.06
A47: 库存周转专项 | B47: 张珂铜 | C47: 库存周转 | D47: 张珂铜 | E47: 库存周转天数 | F47: 3、4、5缺少月度目标 周期初、末总成本均值为A，周期内发货成本B 库存周转天数=周期天数/（B/A） 基线数据：以2026年3月为基线 目标值：全年库存周转天数达到55天（12月） 目标进度：目标值/实际值 | G47: 财务数据 （袁子清） | H47: 定义清晰 | I47: 次月18日提供 | J47: 是 | K47: 否 | L47: 348 | M47: 55 | N47: — | O47: — | P47: — | Q47: 120 | R47: 110 | S47: 100 | T47: 90 | U47: 80 | V47: 70 | W47: 55
A48: 库存周转专项 | B48: 张珂铜 | C48: 发货准确率 | D48: 崔凯旋 | E48: SWGT发货预测准确率-1周 | F48: min(当周发货数/预测数,当周预测数/发货数 基线数据：20%（本周） 目标值：1周预测准确率100%（左右浮动5%） 目标进度：（实际值-基线值）/(目标值-基线值) | G48: 运营管理部 (徐萍提供 崔凯旋审核) | H48: 定义清晰 | J48: 是 | K48: 否 | L48: 暂无 | M48: 1 | N48: 1 | O48: 1 | P48: 1 | Q48: 1 | R48: 1 | S48: 1 | T48: 1 | U48: 1 | V48: 1 | W48: 1
A49: 库存周转专项 | B49: 张珂铜 | C49: 发货准确率 | D49: 崔凯旋 | E49: SW50发货预测准确率-1周 | F49: 当周发货数/预测数 基线数据：20%（本周） 目标值：1周预测准确率100%（左右浮动5%） 目标进度：（实际值-基线值）/(目标值-基线值) | G49: 运营管理部 (徐萍提供 崔凯旋审核) | H49: 定义清晰 | J49: 是 | K49: 否 | L49: 暂无 | M49: 1 | N49: 1 | O49: 1 | P49: 1 | Q49: 1 | R49: 1 | S49: 1 | T49: 1 | U49: 1 | V49: 1 | W49: 1
A50: 库存周转专项 | B50: 张珂铜 | C50: 发货准确率 | D50: 崔凯旋 | E50: Titan810发货预测准确率-1周 | F50: 当周发货数/预测数 基线数据：20%（本周） 目标值：1周预测准确率100%（左右浮动5%） 目标进度：（实际值-基线值）/(目标值-基线值) | G50: 运营管理部 (徐萍提供 崔凯旋审核) | H50: 定义清晰 | J50: 是 | K50: 否 | L50: 暂无 | M50: 1 | N50: 1 | O50: 1 | P50: 1 | Q50: 1 | R50: 1 | S50: 1 | T50: 1 | U50: 1 | V50: 1 | W50: 1
A51: 库存周转专项 | B51: 张珂铜 | C51: 发货准确率 | D51: 崔凯旋 | E51: SWGT发货预测准确率-4周 | F51: 4周滚动预测准确率---没有4周？ 基线数据：暂无 目标值：4周预测准确率≥85% 目标进度：（实际值-基线值）/(目标值-基线值) | G51: 运营管理部 (徐萍提供 崔凯旋审核) | H51: 定义清晰 | J51: 是 | K51: 否 | L51: 暂无 | M51: 0.85 | N51: 0.8 | O51: 0.8 | P51: 0.8 | Q51: 0.85 | R51: 0.85 | S51: 0.85 | T51: 0.85 | U51: 0.85 | V51: 0.85 | W51: 0.85
A52: 库存周转专项 | B52: 张珂铜 | C52: 发货准确率 | D52: 崔凯旋 | E52: SW50发货预测准确率-4周 | F52: 4周滚动预测准确率---没有4周？ 基线数据：暂无 目标值：4周预测准确率≥85% 目标进度：（实际值-基线值）/(目标值-基线值) | G52: 运营管理部 (徐萍提供 崔凯旋审核) | H52: 定义清晰 | J52: 是 | K52: 否 | L52: 暂无 | M52: 0.85 | N52: 0.8 | O52: 0.8 | P52: 0.8 | Q52: 0.85 | R52: 0.85 | S52: 0.85 | T52: 0.85 | U52: 0.85 | V52: 0.85 | W52: 0.85
A53: 库存周转专项 | B53: 张珂铜 | C53: 发货准确率 | D53: 崔凯旋 | E53: Titan810发货预测准确率-4周 | F53: 4周滚动预测准确率---没有4周？ 基线数据：暂无 目标值：4周预测准确率≥85% 目标进度：（实际值-基线值）/(目标值-基线值) | G53: 运营管理部 (徐萍提供 崔凯旋审核) | H53: 定义清晰 | J53: 是 | K53: 否 | L53: 暂无 | M53: 0.85 | N53: 0.8 | O53: 0.8 | P53: 0.8 | Q53: 0.85 | R53: 0.85 | S53: 0.85 | T53: 0.85 | U53: 0.85 | V53: 0.85 | W53: 0.85
A54: 库存周转专项 | B54: 张珂铜 | C54: 发货准确率 | D54: 崔凯旋 | E54: SWGT发货预测准确率-5周 | F54: 5周滚动预测准确率--暂无数据 基线数据：暂无 目标值：5周预测准确率≥70% 目标进度：（实际值-基线值）/(目标值-基线值) | G54: 运营管理部 (徐萍提供 崔凯旋审核) | H54: 定义清晰 | J54: 是 | K54: 否 | L54: 暂无 | M54: 0.7 | N54: 0.65 | O54: 0.65 | P54: 0.67 | Q54: 0.7 | R54: 0.7 | S54: 0.7 | T54: 0.7 | U54: 0.7 | V54: 0.7 | W54: 0.7
A55: 库存周转专项 | B55: 张珂铜 | C55: 发货准确率 | D55: 崔凯旋 | E55: SW50发货预测准确率-5周 | F55: 5周滚动预测准确率--暂无数据 基线数据：暂无 目标值：5周预测准确率≥70% 目标进度：（实际值-基线值）/(目标值-基线值) | G55: 运营管理部 (徐萍提供 崔凯旋审核) | H55: 定义清晰 | J55: 是 | K55: 否 | L55: 暂无 | M55: 0.7 | N55: 0.65 | O55: 0.65 | P55: 0.67 | Q55: 0.7 | R55: 0.7 | S55: 0.7 | T55: 0.7 | U55: 0.7 | V55: 0.7 | W55: 0.7
A56: 库存周转专项 | B56: 张珂铜 | C56: 发货准确率 | D56: 崔凯旋 | E56: Titan810发货预测准确率-5周 | F56: 5周滚动预测准确率--暂无数据 基线数据：暂无 目标值：5周预测准确率≥70% 目标进度：（实际值-基线值）/(目标值-基线值) | G56: 运营管理部 (徐萍提供 崔凯旋审核) | H56: 定义清晰 | J56: 是 | K56: 否 | L56: 暂无 | M56: 0.7 | N56: 0.65 | O56: 0.65 | P56: 0.67 | Q56: 0.7 | R56: 0.7 | S56: 0.7 | T56: 0.7 | U56: 0.7 | V56: 0.7 | W56: 0.7
A57: 预算管理能力提升专项 | B57: 袭丽丽 | C57: / | D57: 袭丽丽 | E57: 主营业务经营性现金流 | F57: 主营业务经营性现金流净额（财务报表数据） 月度目标为单月目标，非年度累积 基线数据：暂无 目标值：主营业务经营性现金流为正 目标进度：（实际值-基线值）/(目标值-基线值) | G57: 财务数据 袁子清 | H57: 定义清晰 | I57: 次月18日提供 | J57: 是 | K57: 否 | M57: 0 | N57: -223.16 | O57: -790.43 | P57: -771.14 | Q57: 241.12 | R57: -227 | S57: 731.12 | T57: 90.5 | U57: 879 | V57: 1456.56 | W57: 1246.03
A58: 核算能力提升专项 | B58: 袭丽丽 | C58: / | D58: 袭丽丽 | E58: 财务报表出具时效 | F58: 每月出具财务报表的天数 基线数据：不涉及 目标值：系统上线前每月13日前出报表，系统上线后每月7日前出财务报表 目标进度&每月完成率：达成100分，每推迟一天扣25分 | G58: 财务总监反馈 领导核实 | H58: 定义清晰 | J58: 否 | K58: 否 | L58: 暂无 | M58: 系统上线前每月13日前出报表，系统上线后每月7日前出财务报表 | N58: 协调台账建立，出报表预测 | O58: 按周出收入成本预测数据 | P58: 每周出数据 | Q58: 中台上线 | R58: — | S58: 首次达成7天出报表（中台上线后） | T58: — | U58: — | V58: — | W58: 7天出报表稳定达成
A59: 人力提效专项 | B59: 杨帆 | C59: / | D59: 杨帆 | E59: 万元人力成本收入 | F59: 万元人力成本收入 = 营业收入/人力资源成本 领导比较关注，不在专项跟踪？ 基线数据：暂无 目标值：每1万元人力资源成本带来3万元收入 目标进度：（实际值-基线值）/(目标值-基线值) 无月度目标值 | G59: 财务数据 袁子清 | H59: 人力资源成本定义 定义不明确 | J59: 是 | K59: 否 | N59: 高密度人才到岗、考核方案确定 | O59: — | P59: — | Q59: — | R59: — | S59: — | T59: — | U59: — | V59: — | W59: 万元人力成本≥3万元收入
A60: 人力降费专项 | B60: 杨帆 | C60: / | D60: 杨帆 | E60: 人力相关费用节约 | F60: 劳务服务费+猎头费+招聘费实际支出对比上年降低额 基线数据：0 目标值：降低46万元 月度完成率：以里程碑活动计，完成且开始降费得100分；完成但未降费，未完成但降费得70分；未完成且未降费得40分。 目标进度：实际值/基线值 | G60: 财务数据 袁子清 | H60: 人力资源成本定义 定义不明确 | J60: 是 | K60: 否 | N60: — | O60: 深圳主体成立（4月30日） | P60: 用工方式切换（5月15日），代理20人、外包14人 | Q60: — | R60: — | S60: — | T60: — | U60: — | V60: — | W60: 累计节约46万元

Sheet 项目里程碑
A1: 专项名称 | B1: 专项负责人 | C1: 子专项 | D1: 子专项责任人 | E1: 目标名称 | F1: 关键里程碑 | G1: 里程碑时间点 | H1: 里程碑事件 | I1: 达成情况 | J1: 达成情况说明
A2: MTPF提升专项 | B2: 徐融 | C2: / | D2: 徐融 | E2: SWGT MTPF平均故障间隔时间（小时） SW50 MTPF平均故障间隔时间（小时） Titan810 MTPF平均故障间隔时间（小时） SWGT "1460"指标（小时） SW50 "1460"指标（小时） Titan810 "1460"指标（小时） | F2: 研发分阶段提供提升专项版本 | G2: 46142 | H2: 发布一个专项版本（V1）
G3: 46203 | H3: 研发框架重构完成 + 工单问题解决50%
G4: 46234 | H4: 发布一个专项版本（V2）
G5: 46326 | H5: 发布一个专项版本（V3）
G6: 46387 | H6: 工单问题解决超过85%，MTBF和1460指标分别达成400h和2000h
F7: 质量跟踪工单TOP问题解决 | G7: 46112 | H7: 各月跟踪jira回归和关闭的执行情况
G8: 46142 | H8: 各月跟踪jira回归和关闭的执行情况
G9: 46173 | H9: 各月跟踪jira回归和关闭的执行情况
G10: 46203 | H10: 各月跟踪jira回归和关闭的执行情况
G11: 46234 | H11: 各月跟踪jira回归和关闭的执行情况
G12: 46265 | H12: 各月跟踪jira回归和关闭的执行情况
G13: 46295 | H13: 各月跟踪jira回归和关闭的执行情况
G14: 46326 | H14: 各月跟踪jira回归和关闭的执行情况
G15: 46356 | H15: 各月跟踪jira回归和关闭的执行情况
G16: 46387 | H16: 各月跟踪jira回归和关闭的执行情况
F17: 工程服务完成涉及现场的版本部署 | G17: 46172 | H17: 专项版本（V1）60%部署
G18: 46203 | H18: 专项版本（V1）100%部署
G19: 46265 | H19: 专项版本（V2）60%部署
G20: 46295 | H20: 专项版本（V2）100%部署
G21: 46356 | H21: 专项版本（V3）60%部署
G22: 46387 | H22: 专项版本（V3）100%部署
A23: 8H部署专项 | B23: 崔凯旋 | C23: / | D23: 崔凯旋 | E23: SWGT 部署时长（小时） Titan810 部署时长（小时） | F23: SW GT按照MRD完成易部署功能开发 | G23: 46142 | H23: 4月15日完成第一阶段开发，4月30日上线
G24: 46234 | H24: 6月30日完成第二阶段功能开发，7月30日上线
G25: 46295 | H25: 预研功能（远程部署支持），9月30日上线
F26: Titan 810产品按照MRD完成易部署功能开发 | G26: 46127 | H26: 4月15日完成Titan 810产品易部署MRD评审
G27: 46142 | H27: 4月30日完成易部署功能开发计划评审FAE完成培训和部署流程优化
F28: FAE能力建设，部署能力提升 | G28: 46119 | H28: 4月7日输出Q1部署总结
G29: 46203 | H29: 6月30日完成FAE集中培训
G30: 46210 | H30: 7月7日输出Q2部署总结
G31: 46264 | H31: 基于SW GT易部署第二阶段功能上线，FAE在8月30日完成培训
A32: 数字中台专项 | B32: 季明清 | C32: / | D32: 季明清 | E32: MES上线 | F32: 硬件部署与系统导入 | G32: 46142 | H32: 核心任务：完成服务器硬件架设，完成CRM上线、启动用友ERP财务系统部署。 验收标准：服务器集群搭建完成，用友系统基础环境就绪，流程初步确认，服务器网络与算力稳定可用，CRM正式上线使用、用友系统部署启动，核心业务流程完成梳理。
F33: 系统联调与测试 | G33: 46142 | H33: 核心任务：MES系统上线，中台升级对接新系统，完成数据清洗。完成ERP内部方案论证、方案测试和确认、各业务静态数据准备、测试、集成开发测试以及二轮业务测试。 验收标准：MES系统接管生产订单、领料、生产全流程，生产业务由自研 MES 稳定承接，用友系统完成培训和试用，可正常操作。
E34: 三流合一 | F34: 上线冲刺与试运行 | G34: 46203 | H34: 核心任务：完成用友正式环境构建、集成代码部署、各业务静态数据完善、期初数据采集及核对，打通经营全流程，上线管理看板。 验收标准：中台完成与新CRM、用友接口对接，实现数据实时传输，核心经营流程跑通，管理看板可展示关键业务数据。
F35: 关键流程打通与看板上线 | G35: 46203 | H35: 核心任务：完成全流程闭环验证，全新数字中台正式投入使用，支撑月底结账、报表出具，确保无问题后进行项目验收。 验收标准：全新数字中台上线替换原有系统，系统运行稳定，核心经营看板可支撑决策，达成“三流合一”阶段性目标。
E36: 0号员工上线 | F36: 完成AI基础能力搭建 | G36: 46265 | H36: 核心任务：构建统一的算力管理知识库和agent能力，为“0 号员工”智能体提供底层支撑。 验收标准：完成算力租赁、接入、调度，满足“0 号员工”模型训练与推理的资源需求，企业级核心知识完成结构化入库，基础agent框架可调用数据与知识并验证典型业务场景，形成适配“0 号员工”的开发规范与能力清单。
F37: “0 号员工”上线 | G37: 46265 | H37: 核心任务：对数据中台业务进行系统分析与评估，深度融入经营分析工作，基于数据洞察主动输出决策建议，形成从“分析”到“决策”再到“业务闭环”的全链路支撑。 验收标准：实现AI数字交互，完成信息流、资金流、物流的数据汇总与分析，支撑公司运营管理，为管理层提供决策依据。
A38: 质量提升专项 | B38: 吴赛 | C38: 合同质量 | D38: 张海滨 | E38: 合同质量-异常率 合同质量-非正常优惠率 | F38: 筹备成长期（第二季度末） | G38: 46203 | H38: 1.核心成果：完成签单商务流程梳理、合同变更管控标准制定、非正常优惠合同界定标准及审核流程出台，搭建商务质量监控体系，完善变更管控与优惠审批机制，实现商务质量初步提升，形成标准化管控模式。制定培训方案，框定培训内容，选定培训标杆案例。 2.目标拆解：合同异常率降至6%以内、非正常优惠合同比例降至12%以内，完成商务质量管控流程试点落地并优化。
F39: 冲刺提升期（第3季度末） | G39: 46295 | H39: 1.核心成果：达成全年核心目标，合同异常率、非正常优惠合同比例均达标，形成可复用的商务质量管控经验。分战区组织培训，进行培训效果评价。 2.目标拆解：合同异常率控制在5%以下、非正常优惠合同比例控制在10%以内，巩固管控效果，减少违规情况。
F40: 闭环收尾期（第4季度末） | G40: 46387 | H40: 1.核心成果：全年商务质量目标持续达标，优化管控流程，复盘全年工作，形成下一年度商务质量提升计划。 2.目标拆解：合同异常率稳定≤5%、非正常优惠合同比例稳定≤10%，完成全年商务质量复盘，优化管控措施。
C41: 研发质量 | D41: 袁德明 | E41: 研发质量-SWGT测试泄漏率 研发质量-Titan810测试泄漏率 | F41: 测试泄漏率降低 | G41: 46203 | H41: 版本测试自动化：6月试点，后续例行
G42: 46234 | H42: 开发代码静动态审查:7月纳入门禁，后续例行解决问题
G43: 46203 | H43: 完成Q2现场问题专项排雷
G44: 46295 | H44: 完成Q3现场问题专项排雷
G45: 46387 | H45: 完成Q4现场问题专项排雷
G46: 46203 | H46: 测试场景仿真和测试用例库建设：Q2确认场景范围，管理方式和管理工具，后续例行补充测试场场景库
E47: 研发质量-JIRA及时关闭率 | F47: JIRA关闭提升 | G47: 46142 | H47: 团队及个人jira问题处理进展上大屏，实时通报：4月上线
G48: 46173 | H48: 长期未解决（90天）jira单每周专项解决，通报：5月首次通报，后续每月例行
G49: 46173 | H49: jira处理进展纳入员工绩效：5月实施，后续例行
G50: 46173 | H50: JIRA处理流程优化，应用自动化工具提升效率：5月优化工作流
G51: 46265 | H51: JIRA处理流程优化，应用自动化工具提升效率：8月应用自动化工具
C52: 采购质量 | D52: 巴路瑶 | E52: 采购质量-来料批次不良 | F52: 体系搭建与标准夯实 | G52: 46203 | H52: （4月-6月），确保来料检验有法可依，异常处理有章可循。核心：规范检验流程，杜绝不合格批次流入。
F53: 深度审核与精准优化 | G53: 46295 | H53: （7月-9月），通过深入供应商现场审核与内部检验策略优化，提升质量管控的颗粒度与应对突发异常的能力。
F54: 优胜劣汰与全面闭环 | G54: 46387 | H54: （10月-12月），通过淘汰机制清理质量隐患，复盘全年数据，为下一年度建立高质量的供应体系。核心：强化供应商管理，从源头规避质量风险。
F55: 消除独家 | G55: 46203 | H55: GT非独家供应商占比达85%，T810非独家供应商占比达65%（4~6月）
F56: 三结合体系搭建 | G56: 46265 | H56: 三结合模块完成供应商体系搭建（4月—8月）
C57: 生产质量 | D57: 吴赛 | E57: 生产过程质量-SWGT 开箱合格率 生产过程质量-SW50 开箱合格率 生产过程质量-Titan810 开箱合格率 生产过程质量-SWGT 90天内维修率 生产过程质量-SW50 90天内维修率 生产过程质量-Titan810 90天内维修率 | F57: 现状排查及生产过程管控 | G57: 46203 | H57: 现状排查及生产过程管控，建立包装标准化作业指导书，明确包装紧固方式（4~6月）
F58: 检测过程优化 | G58: 46265 | H58: 检测过程优化，推行工位扫码质检机制，每个关键组装工位完成操作后扫码上传质检数据（7~8月）
F59: 人员能力提升 | G59: 46326 | H59: 人员能力提升，实施关键工序100%防错，对核心部件安装、参数调试等工序引入防错装置自动化设备（9~10月）
F60: 流程闭环优化 | G60: 46387 | H60: 流程闭环优化，建立下线全性能测试标准，覆盖所有功能模块，测试数据自动上传MES系统（11~12月）
C61: 售后质量 | D61: 崔凯旋 | E61: 售后质量-问题一次性解决率 售后质量-平均解决时效（一线城市）（小时） 售后质量-平均解决时效（二线城市）（小时） 售后质量-平均解决时效（海外核心国家）（小时） 售后质量-平均解决时效（海外其他国家）（小时） | F61: 服务工单系统上线，全量服务数据电子化 | G61: 46203
F62: 全球售后备件仓搭建完毕，满足及时的配件交付 | G62: 46203 | H62: 国内：6月中心仓库准备完毕
G63: 46295 | H63: 国内：9月前置仓准备完毕
G64: 46203 | H64: 海外：6月欧洲、北美建立中心仓库
G65: 46356 | H65: 海外：11月，前置仓准备完毕；
F66: 第三方服务完善，增加服务覆盖率，确保及时响应 | G66: 46295 | H66: 9月：服务商24小时接单率95%；
G67: 46356 | H67: 11月：第三方服务占比40%
F68: 维修赋能，AI提效，确保客户需求不同复杂程度维修有合适能力的维修人员满足 | G68: 46203 | H68: 零号员工上线接单；通过系统拿到FAE一次解决率真实数据；
G69: 46295 | H69: 第三方服务一次解决率90%
F70: 服务代理商（包含销售代理商）能力建设 | G70: 46387 | H70: 完成公司外包管理标准（服务商选择，签署，培训、验收、淘汰）
G71: 46387 | H71: 完成10次+代理商培训
A72: 渠道管理能力提升 | B72: 张海滨 | C72: 经销商收入 | D72: 张海滨 | E72: 经销商收入（累计） 新增经销商数量（月新增） 经销商存销比 经销商复购率 | F72: 一级里程碑1：（第2季度末） | G72: 46203 | H72: 核心成果：新增经销商落地合作、存销比达标、复购率稳步提升，经销商动销能力增强。 ￮目标拆解：累计新增15个经销商、收入达到4600万、存销比稳定2:1、复购率达25%。
F73: 一级里程碑2：冲刺提升期（第3季度末） | G73: 46295 | H73: 核心成果：完成20个新增经销商目标、复购率达标，收入冲刺至全年40%。 ￮目标拆解：累计新增20个经销商、收入11000万、存销比维持1.5:1、复购率达70%。
F74: 一级里程碑3：闭环收尾期（第4季度末） | G74: 46387 | H74: 核心成果：完成全年收入目标，经销商体系优化，形成可复用管理模式。 ￮目标拆解：收入1.6亿、存销比与复购率持续达标，30个新增经销商稳定运营。
C75: 经销商服务收费 | D75: 崔凯旋 | E75: 累计收费服务经销商占比超过35% | F75: 一级里程碑1：（第2季度末） | G75: 46203 | H75: ￮核心成果：经销商POC、开局、现场服务等收费标准确定。 ￮目标拆解：服务收费目标经销商确定（不少于总经销商数量的40%），服务收费标准与竞争对手的对比。
F76: 一级里程碑2：冲刺提升期（第3季度末） | G76: 46295 | H76: ￮核心成果：完成国内国际所有新签经销商的服务收费合同确立，整体实现服务收费项目的经销商数量达到20%， ￮目标拆解：国际经销商收费数量达到30%个，国内数量10%、
F77: 一级里程碑3：冲刺加速期（第4季度末） | G77: 46387 | H77: ￮核心成果：实现国外经销商60%，国内30%比例的经销商合同服务比例 ￮目标拆解：国际经销商服务收费数量达到50%，国内达到25%
A78: Marketing能力提升 | B78: 张海滨 | C78: / | D78: 张海滨 | E78: 毛利率 应收周转天数 | F78: 一级里程碑1：筹备成长期（2季度末） | G78: 46203 | H78: 核心成果：搭建毛利率与应收周转监控体系，明确核算标准，完成基准数据复盘，指标初步优化，为全年目标奠定基础。毛利率逐步提升，应收周转效率优化，形成标准化管控流程，指标接近全年目标。 ￮目标拆解：毛利率≥40%、应收周转≤55天，完善管控流程，解决核心管控难点。
F79: 一级里程碑2：冲刺提升期（第3季度末） | G79: 46295 | H79: ￮核心成果：两大指标全部达成全年目标，形成可复用的管控模式，维持指标稳定。 ￮目标拆解：毛利率≥50%（达成全年目标）、应收周转≤46天（达成全年目标），巩固管控效果。
F80: 一级里程碑3：闭环收尾期（第4季度末） | G80: 46387 | H80: ￮核心成果：全年毛利率、应收周转指标持续稳定达标，复盘管控经验，优化下一年度管控计划。 ￮目标拆解：毛利率稳定≥60%、应收周转稳定≤40天，完成全年复盘与优化。
A81: 政府资金专项 | B81: 何波 | C81: / | D81: 何波 | E81: 政府资金到账额（万元） | F81: 到账金额300万元 | G81: 46112
F82: 1、C17栋减免2026年房租155万元； 2、红枫科技园2026年房租减免432万元； | G82: 46142
F83: 150万元到账 | G83: 46173
F84: 红枫科技园装修款500万元 | G84: 46265
F85: 申报省级双创团队（具体申报时间以南京市人才办发布申报通知为准） | G85: 46326
F86: 嘉兴南湖750万到账。 80万元到账；500万元获批； | G86: 46387
E87: 新增政府资金获批（万元） | F87: 南京500万 | G87: 46387 | H87: 南京政府资金，500万元获批；
F88: 嘉兴1500万 | G88: 46173 | H88: 完成嘉兴项目公司注册及人才项目申请主体公司注册；
G89: 46234 | H89: （1）申报创业人才项目；（2）生产性设备投资3000万元以上，设备采购合同、发票、流水一致，可申请设备投资补助300万元。（3）3000平米厂房免租六个月，节约租金约45万元。
G90: 46356 | H90: 获批1345万元；剩余155万元根据公司研发投入情况而定。
F91: 深圳1000万 | G91: 46142 | H91: 收集深圳市南山区、龙岗区、河套园区等地政策；
G92: 46203 | H92: 2026年6月：评估实现路径及所需条件；注册深圳落地公司；
G93: 46234 | H93: 2026年7月：制定达成方案
G94: 46356 | H94: 2026年11月：满足条件后获批1000万元；
A95: 降本专项 | B95: 巴路瑶 | C95: 非独家占比 | D95: 陈栋力 | E95: GT非独家物料占比 | F95: 一类物料完成度达到90% | G95: 46203
F96: 二类物料完成度达到75% | G96: 46203
F97: 三类物料完成度达到90% | G97: 46203
F98: 四类物料完成度达到50% | G98: 46203
E99: T810非独家物料占比 | F99: 一类物料完成度达到70% | G99: 46203
F100: 二类物料完成度达到60% | G100: 46203
...

Sheet 项目计划
A1: 序号 | B1: 专项 | C1: 级别 | D1: 关键活动 | E1: 责任人 | F1: 完成时间 | G1: 对应指标 | H1: 验收标准
A2: 1 | B2: MTPF提升专项 | C2: 一级 | D2: 研发框架重构完成 + 工单问题解决50% | F2: 46203 | G2: MTPF、1460指标
A3: 2 | B3: MTPF提升专项 | C3: 一级 | D3: 工单问题解决超过85%，MTBF和1460指标分别达成400h和200h | F3: 46387 | G3: MTPF、1460指标
A4: 3 | B4: MTPF提升专项 | C4: 一级 | D4: M4发布一个专项版本 | F4: 46142 | G4: MTPF、1460指标
A5: 4 | B5: MTPF提升专项 | C5: 一级 | D5: 完成M4版本工程部署：部署率60% | F5: 46173 | G5: MTPF、1460指标
A6: 5 | B6: MTPF提升专项 | C6: 一级 | D6: 完成M4版本工程部署：部署率100% | F6: 46203 | G6: MTPF、1460指标
A7: 6 | B7: MTPF提升专项 | C7: 一级 | D7: M7发布一个专项版本 | F7: 46234 | G7: MTPF、1460指标
A8: 7 | B8: MTPF提升专项 | C8: 一级 | D8: 完成M7版本工程部署：部署率60% | F8: 46265 | G8: MTPF、1460指标
A9: 8 | B9: MTPF提升专项 | C9: 一级 | D9: 完成M7版本工程部署：部署率100% | F9: 46295 | G9: MTPF、1460指标
A10: 9 | B10: MTPF提升专项 | C10: 一级 | D10: M10发布一个专项版本 | F10: 46326 | G10: MTPF、1460指标
A11: 10 | B11: MTPF提升专项 | C11: 一级 | D11: 完成M10版本工程部署：部署率60% | F11: 46356 | G11: MTPF、1460指标
A12: 11 | B12: MTPF提升专项 | C12: 一级 | D12: 完成M10版本工程部署：部署率100% | F12: 46387 | G12: MTPF、1460指标
A13: 12 | B13: MTPF提升专项 | C13: 一级 | D13: 【质量跟踪工单TOP问题解决】M3跟踪jira回归和关闭的执行情况 2.1 跟踪Jira工单回归执行情况 每月 2.1.1 每月3日前拉取上月“已解决”状态工单清单（每月W1）：输出待回归工单清单 2.1.2 组织测试/工程资源进行回归验证（每月W2-W3）：输出回归测试报告 2.1.3 将回归不通过的工单打回研发重新处理（每月W4）：输出退回工单记录 2.2 跟踪Jira工单关闭执行情况 每月 2.2.1 每月25日前确认已通过回归的工单是否现场已部署（每月W4）：输出待关闭工单清单 2.2.2 推动责任方完成工单关闭操作（每月W4）：输出关闭工单记录 2.2.3 输出每月工单闭环率报表（每月末）：输出闭环率报表 | F13: 46112 | G13: MTPF、1460指标
... A52: 51 | B52: “8H”部署专项 | C52: 一级 | D52: SW GT按照MRD完成易部署功能开发， 4月30日完成第一阶段上线 | F52: 46142 | G52: SW GT 部署时长
A53: 52 | B53: “8H”部署专项 | C53: 一级 | D53: SW GT按照MRD完成易部署功能开发，6月30日完成第二阶段功能开发 | F53: 6月30日 | G53: SW GT 部署时长
A54: 53 | B54: “8H”部署专项 | C54: 一级 | D54: SW GT按照MRD完成易部署功能开发，7月30日上线第二阶段功能 | F54: 46233 | G54: SW GT 部署时长
A55: 54 | B55: “8H”部署专项 | C55: 一级 | D55: SW GT按照MRD完成易部署功能开发，预研功能 ，9月30日上线； | F55: 9月30日 | G55: SW GT 部署时长
A56: 55 | B56: “8H”部署专项 | C56: 一级 | D56: Titan 810产品按照MRD完成易部署功能开发：4月15日完成Titan 810产品易部署MRD评审 | F56: 4月15日 | G56: Titan 810 部署时长
A57: 56 | B57: “8H”部署专项 | C57: 一级 | D57: Titan 810产品按照MRD完成易部署功能开发：4月30日完成易部署功能开发计划评审 | F57: 4月30日 | G57: Titan 810 部署时长
A58: 57 | B58: “8H”部署专项 | C58: 一级 | D58: FAE部署能力提升： 4月7日输出Q1部署总结 | F58: 4月7日 | G58: SW GT 部署时长、Titan 810 部署时长
A59: 58 | B59: “8H”部署专项 | C59: 一级 | D59: 基于Titan易部署功能第一阶段功能上线，FAE在4月30日完成培训和部署流程优化； | F59: 46142 | G59: SW GT 部署时长、Titan 810 部署时长
A60: 59 | B60: “8H”部署专项 | C60: 一级 | D60: FAE部署能力提升：6月31日完成FAE集中培训 | F60: 46203 | G60: SW GT 部署时长、Titan 810 部署时长
A61: 60 | B61: “8H”部署专项 | C61: 一级 | D61: FAE部署能力提升：7月7日输出Q2部署总结 | F61: 7月7日 | G61: SW GT 部署时长、Titan 810 部署时长
A62: 61 | B62: “8H”部署专项 | C62: 一级 | D62: 基于SW GT易部署第二阶段功能上线，FAE在8月30日完成培训 | F62: 8月30日 | G62: SW GT 部署时长
A63: 62 | B63: “8H”部署专项 | C63: 二级 | D63: 3月31日服务侧梳理Q1部署期间物料更换/漏发 | F63: 46112 | G63: SW GT 部署时长、Titan 810 部署时长
A64: 63 | B64: “8H”部署专项 | C64: 二级 | D64: 服务侧梳理交付流程进行优化 | F64: 无计划 | G64: SW GT 部署时长、Titan 810 部署时长
A65: 64 | B65: “8H”部署专项 | C65: 二级 | D65: Q2每月组织FAE部署经验分享和复盘-4月 | F65: 4月30日 | G65: SW GT 部署时长、Titan 810 部署时长
A66: 65 | B66: “8H”部署专项 | C66: 二级 | D66: Q2每月组织FAE部署经验分享和复盘-5月 | F66: 46173 | G66: SW GT 部署时长、Titan 810 部署时长
A67: 66 | B67: “8H”部署专项 | C67: 二级 | D67: Q2每月组织FAE部署经验分享和复盘-6月 | F67: 46203 | G67: SW GT 部署时长、Titan 810 部署时长
A68: 67 | B68: “8H”部署专项 | C68: 二级 | D68: FAE季度培训，认证和能力验收-Q2 | F68: 46203 | G68: SW GT 部署时长、Titan 810 部署时长
A69: 68 | B69: “8H”部署专项 | C69: 二级 | D69: FAE季度培训，认证和能力验收-Q3 | F69: 9月30日 | G69: SW GT 部署时长、Titan 810 部署时长
A70: 69 | B70: “8H”部署专项 | C70: 二级 | D70: FAE季度培训，认证和能力验收-Q4 | F70: 46387 | G70: SW GT 部署时长、Titan 810 部署时长
A71: 70 | B71: 数字中台专项 | C71: 一级 | D71: 硬件部署与系统导入：完成服务器硬件架设，完成CRM上线、启动用友ERP财务系统部署。 | F71: 46112 | G71: MES上线 | H71: 服务器集群搭建完成，用友系统基础环境就绪，流程初步确认，服务器网络与算力稳定可用，CRM正式上线使用、用友系统部署启动，核心业务流程完成梳理。
A72: 71 | B72: 数字中台专项 | C72: 一级 | D72: 系统联调与测试：MES系统上线，中台升级对接新系统，完成数据清洗。完成ERP内部方案论证、方案测试和确认、各业务静态数据准备、测试、集成开发测试以及二轮业务测试。 | F72: 46142 | G72: MES上线 | H72: MES系统接管生产订单、领料、生产全流程，生产业务由自研 MES 稳定承接，用友系统完成培训和试用，可正常操作。
A73: 72 | B73: 数字中台专项 | C73: 一级 | D73: 上线冲刺与试运行：完成用友正式环境构建、集成代码部署、各业务静态数据完善、期初数据采集及核对，打通经营全流程，上线管理看板。 | F73: 46173 | G73: 三流合一 | H73: 中台完成与新CRM、用友接口对接，实现数据实时传输，核心经营流程跑通，管理看板可展示关键业务数据。
A74: 73 | B74: 数字中台专项 | C74: 一级 | D74: 关键流程打通与看板上线：完成全流程闭环验证，全新数字中台正式投入使用，支撑月底结账、报表出具并，确保无问题后进行项目验收。 | F74: 46203 | G74: 三流合一 | H74: 全新数字中台上线替换原有系统，系统运行稳定，核心经营看板可支撑决策，达成“三流合一”阶段性目标。
A75: 74 | B75: 数字中台专项 | C75: 一级 | D75: 完成AI基础能力搭建：构建统一的算力管理知识库和agent能力，为“0 号员工”智能体提供底层支撑 | F75: 46234 | G75: 0号员工上线 | H75: 完成算力租赁、接入、调度，满足“0 号员工”模型训练与推理的资源需求，企业级核心知识完成结构化入库，基础agent框架可调用数据与知识并验证典型业务场景，形成适配“0 号员工”的开发规范与能力清单。
A76: 75 | B76: 数字中台专项 | C76: 一级 | D76: “0 号员工”上线：对数据中台业务进行系统分析与评估，深度融入经营分析工作，基于数据洞察主动输出决策建议，形成从“分析”到“决策”再到“业务闭环”的全链路支撑。 | F76: 46265 | G76: 0号员工上线 | H76: 实现AI数字交互，完成信息流、资金流、物流的数据汇总与分析，支撑公司运营管理，为管理层提供决策依据。
A77: 76 | B77: 质量提升专项 | C77: 一级 | D77: 一级里程碑1：筹备成长期 1.核心成果：完成签单商务流程梳理、合同变更管控标准制定、非正常优惠合同界定标准及审核流程出台，搭建商务质量监控体系，完善变更管控与优惠审批机制，实现商务质量初步提升，形成标准化管控模式。制定培训方案，框定培训内容，选定培训标杆案例。 2.目标拆解：合同异常率降至6%以内、非正常优惠合同比例降至12%以内，完成商务质量管控流程试点落地并优化。 | F77: 46203 | G77: 合同质量-异常率、合同质量-非正常优惠率
A78: 77 | B78: 质量提升专项 | C78: 一级 | D78: 一级里程碑2：冲刺提升期（第3季度末） 1.核心成果：达成全年核心目标，合同异常率、非正常优惠合同比例均达标，形成可复用的商务质量管控经验。分战区组织培训，进行培训效果评价。 2.目标拆解：合同异常率控制在5%以下、非正常优惠合同比例控制在10%以内，巩固管控效果，减少违规情况。 | F78: 46295 | G78: 合同质量-异常率、合同质量-非正常优惠率
A79: 78 | B79: 质量提升专项 | C79: 一级 | D79: 一级里程碑3：闭环收尾期（第4季度末） 1.核心成果：全年商务质量目标持续达标，优化管控流程，复盘全年工作，形成下一年度商务质量提升计划。 2.目标拆解：合同异常率稳定≤5%、非正常优惠合同比例稳定≤10%，完成全年商务质量复盘，优化管控措施。 | F79: 46387 | G79: 合同质量-异常率、合同质量-非正常优惠率
A80: 79 | B80: 质量提升专项 | C80: 二级 | D80: 二级里程碑2.1（第4个月末）：优化合同审核流程，新增合同变更前置审核环节，确保合同变更率降至7%以内、非正常优惠比例降至14%以内。完成销售人员销售纪律培训。 | F80: 46142 | G80: 合同质量-异常率、合同质量-非正常优惠率
A81: 80 | B81: 质量提升专项 | C81: 二级 | D81: 二级里程碑2.2（第5个月末）：完善非正常优惠合同审批流程（需多级审核），推进管控措施落地，确保合同变更率降至6.5%以内、优惠比例降至13%以内。 | F81: 46173 | G81: 合同质量-异常率、合同质量-非正常优惠率
A82: 81 | B82: 质量提升专项 | C82: 二级 | D82: 二级里程碑2.3（第6个月末）：总结选取典型优质案例和负面案例对全体销售进行定期培训，制定培训方案，框定培训内容，选定培训标杆案例，对于异常较多的区域进行通报处罚。复盘上半年管控效果，优化管控措施，达成季度目标（变更率≤6%、优惠比例≤12%），提交半年度进度报告。 | F82: 46203 | G82: 合同质量-异常率、合同质量-非正常优惠率
A83: 82 | B83: 质量提升专项 | C83: 二级 | D83: 二级里程碑2.1（第7个月末）：强化合同变更前置管控，严控非正常优惠审批，确保合同变更率降至5.5%以内、优惠比例降至11%以内。 | F83: 46234 | G83: 合同质量-异常率、合同质量-非正常优惠率
A84: 83 | B84: 质量提升专项 | C84: 二级 | D84: 二级里程碑2.2（第8个月末）：分战区组织培训，进行培训效果评价。冲刺核心目标，优化管控细节，确保合同变更率≤5%、非正常优惠合同比例≤10%，达成全年目标。 | F84: 46265 | G84: 合同质量-异常率、合同质量-非正常优惠率
A85: 84 | B85: 质量提升专项 | C85: 二级 | D85: 二级里程碑2.3（第9个月末）：巩固管控效果，确保两大指标持续达标，复盘管控漏洞，优化措施，提交三季度进度报告。 | F85: 46295 | G85: 合同质量-异常率、合同质量-非正常优惠率
A86: 85 | B86: 质量提升专项 | C86: 二级 | D86: 二级里程碑3.1（第10个月末）：监控指标稳定性，确保合同变更率、非正常优惠比例持续达标，排查管控漏洞。 | F86: 46326 | G86: 合同质量-异常率、合同质量-非正常优惠率
A87: 86 | B87: 质量提升专项 | C87: 二级 | D87: 二级里程碑3.2（第11个月末）：优化管控流程，解决管控中的难点问题，确保指标无反弹。 | F87: 46356 | G87: 合同质量-异常率、合同质量-非正常优惠率
A88: 87 | B88: 质量提升专项 | C88: 二级 | D88: 二级里程碑3.3（第12个月末）：复盘全年商务质量管控工作，总结经验不足，优化下一年度提升计划，提交全年总结报告。 | F88: 46387 | G88: 合同质量-异常率、合同质量-非正常优惠率
... A124: 123 | B124: 质量提升专项 | C124: 二级 | D124: 问题月结专项组运作，每周拉会一对一推进问题闭环 9~12月 | F124: 46387 | G124: 研发质量-JIRA及时关闭率
A125: 124 | B125: 质量提升专项 | C125: 二级 | D125: 1.1完成现有供应商资质复核，签订质量责任承诺书；4月 | G125: 采购质量-来料批次不良
A126: 125 | B126: 质量提升专项 | C126: 二级 | D126: 1.2开展首次供应商季度考核，筛选优质供应商 5月 | G126: 采购质量-来料批次不良
A127: 126 | B127: 质量提升专项 | C127: 二级 | D127: 1.3针对考核不合格供应商，下达整改通知并跟踪落实.6月 | G127: 采购质量-来料批次不良
A128: 127 | B128: 质量提升专项 | C128: 二级 | D128: 1.4 对核心物料供应商开展首次现场审核 7月 | G128: 采购质量-来料批次不良
A129: 128 | B129: 质量提升专项 | C129: 二级 | D129: 1.5 复核不合格供应商整改效果，不合格者暂停合作 8月 | G129: 采购质量-来料批次不良
A130: 129 | B130: 质量提升专项 | C130: 二级 | D130: 1.6 开展第二次供应商季度考核，优化供应商体系 9月 | G130: 采购质量-来料批次不良
A131: 130 | B131: 质量提升专项 | C131: 二级 | D131: 1.7 对现场审核不合格供应商，终止合作并补充优质供应商 10月 | G131: 采购质量-来料批次不良
A132: 131 | B132: 质量提升专项 | C132: 二级 | D132: 1.8 供应商管控：开展核心供应商二次现场审核，巩固质量管控 11月 | G132: 采购质量-来料批次不良
A133: 132 | B133: 质量提升专项 | C133: 二级 | D133: 1.9 汇总全年供应商考核结果，确定下一年度合作名单 12月 | G133: 采购质量-来料批次不良
A134: 133 | B134: 质量提升专项 | C134: 二级 | D134: 2.1 制定详细来料检验标准，组织检验人员专项培训；4月 | G134: 采购质量-来料批次不良
A135: 134 | B135: 质量提升专项 | C135: 二级 | D135: 2.2 执行双人检验制度，重点核查核心物料检验记录 5月 | G135: 采购质量-来料批次不良
A136: 135 | B136: 质量提升专项 | C136: 二级 | D136: 2.3 开展检验流程自查，整改漏检、误检隐患 6月 | G136: 采购质量-来料批次不良
... A202: 95 | B202: 渠道管理有效性提升 | C202: 二级 | D202: •二级里程碑3.3（第12个月末）：完成全年经销商收入1.6亿目标；30个新增经销商稳定运营、实现盈利；存销比稳定在1.5:1、复购率≥70%；复盘全年任务完成情况，总结经验与不足，优化下一年度经销商管理计划，提交全年总结报告。 | G202: 经销商收入（累计）、新增经销商数量（月新增）、经销商存销比、经销商复购率
A203: 103 | B203: Marketing整体能力提升 | D203: •二级里程碑1.1（第1个月中旬）：明确毛利率核算标准（含成本归集、定价管控）、应收周转核算标准，完成上一年度及当前基准数据复盘，梳理指标差距与核心管控难点。 | G203: 毛利率、应收周转天数
A204: 104 | B204: Marketing整体能力提升 | D204: •二级里程碑1.2：搭建毛利率与应收周转动态监控体系，明确监控频率（每周统计、每月复盘），指定专人负责数据统计与分析，形成初步监控报表。 | G204: 毛利率、应收周转天数
A205: 105 | B205: Marketing整体能力提升 | D205: •二级里程碑1.3（第4个月末）：优化毛利率管控措施（如优化产品成本结构、规范定价策略），推进应收回款激励政策落地，监控指标变化，确保毛利率≥35%、应收周转≤60天。 | G205: 毛利率、应收周转天数
B206: Marketing整体能力提升 | D206: •二级里程碑1.4（第5个月末）：深化管控措施，解决试点中发现的问题，扩大管控范围，确保毛利率≥37%、应收周转≤56天，形成标准化管控流程文档。 | G206: 毛利率、应收周转天数
B207: Marketing整体能力提升 | D207: •二级里程碑1.5（第6个月末）：达成二季度指标目标（毛利率≥40%、应收周转≤55天），复盘上半年管控效果，优化管控策略，提交半年度进度报告。 | G207: 毛利率、应收周转天数
B208: Marketing整体能力提升 | D208: •二级里程碑2.1（第7个月末）：强化毛利率管控，严控成本支出、规范定价，推进应收回款提速，确保毛利率≥59.5%、应收周转≤41天。 | G208: 毛利率、应收周转天数
B209: Marketing整体能力提升 | D209: •二级里程碑2.2（第8个月末）：冲刺全年指标，优化回款流程，严控无效成本，确保毛利率≥60%、应收周转≤40天，达成全年目标，维持指标稳定。 | G209: 毛利率、应收周转天数
B210: Marketing整体能力提升 | D210: •二级里程碑2.3（第9个月末）：巩固管控效果，确保毛利率、应收周转持续达标，复盘三季度管控经验，制定四季度维稳计划，提交三季度进度报告。 | G210: 毛利率、应收周转天数
B211: Marketing整体能力提升 | D211: •二级里程碑3.1（第10个月末）：维持两大指标稳定（毛利率≥52%、应收周转≤45天），监控异常波动，及时调整管控措施，确保无反弹。 | G211: 毛利率、应收周转天数
B212: Marketing整体能力提升 | D212: •二级里程碑3.2（第11个月末）：排查管控漏洞，优化成本管控与回款流程，进一步巩固指标稳定性，确保全年指标不出现偏差。 | G212: 毛利率、应收周转天数
B213: Marketing整体能力提升 | D213: •二级里程碑3.3（第12个月末）：完成全年指标闭环，确保毛利率稳定≥60%、应收周转稳定≤40天，复盘全年管控工作，总结经验不足，优化下一年度管控计划，提交全年总结报告。 | G213: 毛利率、应收周转天数
A214: 111 | B214: 政府资金 | D214: 到账金额300万元 | E214: 何波 | F214: 46112 | G214: 政府资金到账额
A215: 112 | B215: 政府资金 | D215: C17栋减免2026年房租155万元； | E215: 何波 | F215: 46142 | G215: 政府资金到账额
A216: 113 | B216: 政府资金 | D216: 红枫科技园2026年房租减免432万元； | E216: 何波 | F216: 46142 | G216: 政府资金到账额
A217: 114 | B217: 政府资金 | D217: 150万元到账； | E217: 何波 | F217: 46173 | G217: 政府资金到账额
A218: 115 | B218: 政府资金 | D218: 红枫科技园装修款500万元； | E218: 何波、方哲 | F218: 46265 | G218: 政府资金到账额
A219: 116 | B219: 政府资金 | D219: 申报省级双创团队（具体申报时间以南京市人才办发布申报通知为准） ； | E219: 李仁君、陈晨光、张卓 | F219: 46295 | G219: 政府资金到账额
A220: 117 | B220: 政府资金 | D220: 嘉兴南湖750万到账。 | E220: 待定 | F220: 46387 | G220: 政府资金到账额
A221: 118 | B221: 政府资金 | D221: 80万元到账；500万元获批； | E221: 何波 | F221: 46387 | G221: 政府资金到账额
A222: 119 | B222: 政府资金 | D222: 南京政府资金，500万元获批； | E222: 何波 | F222: 46387 | G222: 新增政府资金获批
A223: 120 | B223: 政府资金 | D223: 2026年5月：完成嘉兴项目公司注册及人才项目申请主体公司注册； | E223: 邱未召、杨帆、孙林海 | F223: 46173 | G223: 新增政府资金获批
A224: 121 | B224: 政府资金 | D224: 2026年7月： 申报创业人才项目； 生产性设备投资3000万元以上，设备采购合同、发票、流水一致，可申请设备投资补助300万元。 3000平米厂房免租六个月，节约租金约45万元。 | E224: 邱未召、方哲、杨帆、孙林海 | F224: 46234 | G224: 新增政府资金获批
A225: 122 | B225: 政府资金 | D225: 2026年11月：获批1345万元；剩余155万元根据公司研发投入情况而定。 | E225: 邱未召、石峰、孙林海 | F225: 46356 | G225: 新增政府资金获批
... A229: 126 | B229: 政府资金 | D229: 2026年11月：满足条件后获批1000万元； | E229: 孙林海 | F229: 46356 | G229: 新增政府资金获批
A230: 127 | B230: 降本专项 | D230: 1.一类物料完成度达到90%； | G230: GT非独家物料占比
A231: 128 | B231: 降本专项 | D231: 1.1一类物料寻源选型完成达到100%；（4月底） | G231: GT非独家物料占比
A232: 129 | B232: 降本专项 | D232: 1.2一类物料零部件测试完成达到100%；（5月底） | G232: GT非独家物料占比
A233: 130 | B233: 降本专项 | D233: 1.3一类物料整机适配整机测试完成达到100%；（6月中旬） | G233: GT非独家物料占比
B234: 降本专项 | D234: 1.4一类物料BOM导入完成达到90%；（6月底） | G234: GT非独家物料占比
B235: 降本专项 | D235: 2.二类物料完成度达到75%； | G235: GT非独家物料占比
B236: 降本专项 | D236: 2.1二类物料寻源选型完成达到90%；（5月上旬） | G236: GT非独家物料占比
B237: 降本专项 | D237: 2.2二类物料核心零部件测试完成达到100%；（5月底） | G237: GT非独家物料占比
B238: 降本专项 | D238: 2.3二类物料整机适配整机测试完成达到80%；（6月底） | G238: GT非独家物料占比
B239: 降本专项 | D239: 2.4二类物料BOM导入完成达到75%；（6月底） | G239: GT非独家物料占比
B240: 降本专项 | D240: 3.三类物料完成度达到90%； | G240: GT非独家物料占比
B241: 降本专项 | D241: 3.1完成加工件（钣金，焊接，机加）招标采购工作：（5月底） | G241: GT非独家物料占比
...

Sheet 3月健康度核算
A1: 专项名称 | B1: 专项负责人 | C1: 目标名称 | D1: 目标责任人 | E1: 总得分 | F1: 目标得分 | G1: 计划得分 | H1: 运作得分
A2: MTPF提升专项 | B2: 徐融 | C2: SWGT MTPF平均故障间隔时间（小时） | D2: 徐融 | E2: =SUM(F2:H2) -> 47.36 | F2: ='3月目标达成核算'!M2 -> 27.36 | G2: 10 | H2: 10
A3: MTPF提升专项 | B3: 徐融 | C3: SW50 MTPF平均故障间隔时间（小时） | D3: 徐融 | E3: =SUM(F3:H3) -> 60.24 | F3: ='3月目标达成核算'!M3 -> 40.24 | G3: 10 | H3: 10
A4: MTPF提升专项 | B4: 徐融 | C4: Titan810 MTPF平均故障间隔时间（小时） | D4: 徐融 | E4: =SUM(F4:H4) -> 100 | F4: ='3月目标达成核算'!M4 -> 80 | G4: 10 | H4: 10
A5: MTPF提升专项 | B5: 徐融 | C5: SWGT "1460"指标（小时） | D5: 徐融 | E5: =SUM(F5:H5) -> 20 | F5: ='3月目标达成核算'!M5 -> 0 | G5: 10 | H5: 10
A6: MTPF提升专项 | B6: 徐融 | C6: SW50 "1460"指标（小时） | D6: 徐融 | E6: =SUM(F6:H6) -> 100 | F6: ='3月目标达成核算'!M6 -> 80 | G6: 10 | H6: 10
A7: MTPF提升专项 | B7: 徐融 | C7: Titan810 "1460"指标（小时） | D7: 徐融 | E7: =SUM(F7:H7) -> 100 | F7: ='3月目标达成核算'!M7 -> 80 | G7: 10 | H7: 10
A8: 8H部署专项 | B8: 崔凯旋 | C8: SWGT 部署时长（小时） | D8: 崔凯旋 | E8: =SUM(F8:H8) -> 85.957447 | F8: ='3月目标达成核算'!M8 -> 65.957447 | G8: 10 | H8: 10
A9: 8H部署专项 | B9: 崔凯旋 | C9: Titan810 部署时长（小时） | D9: 崔凯旋 | E9: =SUM(F9:H9) -> 79.840637 | F9: ='3月目标达成核算'!M9 -> 59.840637 | G9: 10 | H9: 10
A10: 数字中台专项 | B10: 季明清 | C10: MES上线 | D10: 季明清 | E10: =SUM(F10:H10) -> 20 | F10: ='3月目标达成核算'!M10 -> 0 | G10: 10 | H10: 10
A11: 数字中台专项 | B11: 季明清 | C11: 三流合一 | D11: 季明清 | E11: =SUM(F11:H11) -> 20 | F11: ='3月目标达成核算'!M11 -> 0 | G11: 10 | H11: 10
A12: 数字中台专项 | B12: 季明清 | C12: 0号员工上线 | D12: 季明清 | E12: =SUM(F12:H12) -> 20 | F12: ='3月目标达成核算'!M12 -> 0 | G12: 10 | H12: 10
A13: 质量提升专项 | B13: 吴赛 | C13: 合同质量-异常率 | D13: 张海滨 | E13: =SUM(F13:H13) -> 20 | F13: ='3月目标达成核算'!M13 -> 0 | G13: 10 | H13: 10
... A60: 人力降费专项 | B60: 杨帆 | C60: 人力相关费用节约 | D60: 杨帆 | E60: =SUM(F60:H60) -> 20 | F60: ='3月目标达成核算'!M60 -> 0 | G60: 10 | H60: 10

Sheet 3月目标达成核算
A1: 专项名称 | B1: 专项负责人 | C1: 目标名称 | D1: 目标责任人 | E1: 计算方式/说明 | F1: 数据来源 | G1: 基线值/底线值 | H1: 年度目标值 | I1: 年度目标进度 | J1: 3月（目标） | K1: 3月（实际） | L1: 3月（达成率） | M1: 3月（得分） 满分80
A2: MTPF提升专项 | B2: 徐融 | C2: SWGT MTPF平均故障间隔时间（小时） | D2: 徐融 | E2: MTPF = 设备运行总时长/运维介入售后工单数 基线数据：Q1作为基线 目标值：12月31日≥400h 年度目标进度：实际值/目标值 | F2: 数字中台 （季明清） | G2: 1.83 | H2: 400 | I2: =K2/H2 -> 0.004275 | J2: 5 | K2: 1.71 | L2: =K2/J2 -> 0.342 | M2: =IF(L2>=1.5,80,IF(L2>=1,60+(L2-1)/0.5*20,IF(L2>=0.5,40+(L2-0.5)/0.5*20,L2/0.5*40))) -> 27.36
A3: MTPF提升专项 | B3: 徐融 | C3: SW50 MTPF平均故障间隔时间（小时） | D3: 徐融 | E3: MTPF = 设备运行总时长/运维介入售后工单数 基线数据：Q1作为基线 目标值：12月31日≥400h 年度目标进度：实际值/目标值 | F3: 数字中台 （季明清） | G3: 1.88 | H3: 400 | I3: =K3/H3 -> 0.006325 | J3: 5 | K3: 2.53 | L3: =K3/J3 -> 0.506 | M3: =IF(L3>=1.5,80,IF(L3>=1,60+(L3-1)/0.5*20,IF(L3>=0.5,40+(L3-0.5)/0.5*20,L3/0.5*40))) -> 40.24
A4: MTPF提升专项 | B4: 徐融 | C4: Titan810 MTPF平均故障间隔时间（小时） | D4: 徐融 | E4: MTPF = 设备运行总时长/运维介入售后工单数 基线数据：Q1作为基线 目标值：12月31日≥400h 年度目标进度：实际值/目标值 | F4: 数字中台 （季明清） | G4: 6.37 | H4: 400 | I4: =K4/H4 -> 0.0221 | J4: 5 | K4: 8.84 | L4: =K4/J4 -> 1.768 | M4: =IF(L4>=1.5,80,IF(L4>=1,60+(L4-1)/0.5*20,IF(L4>=0.5,40+(L4-0.5)/0.5*20,L4/0.5*40))) -> 80
A5: MTPF提升专项 | B5: 徐融 | C5: SWGT "1460"指标（小时） | D5: 徐融 | E5: 1460 = 设备运行总时长/（软件自恢复失败次数+硬件维修次数） 基线数据： 目标值：12月31日≥2000h 年度目标进度：实际值/目标值 | F5: 数字中台 （季明清） 维修单 （郭轶） | G5: / | H5: 2000 | I5: =K5/H5 -> 0 | J5: 570 | L5: =K5/J5 -> 0 | M5: =IF(L5>=1.5,80,IF(L5>=1,60+(L5-1)/0.5*20,IF(L5>=0.5,40+(L5-0.5)/0.5*20,L5/0.5*40))) -> 0
A6: MTPF提升专项 | B6: 徐融 | C6: SW50 "1460"指标（小时） | D6: 徐融 | E6: 1460 = 设备运行总时长/（软件自恢复失败次数+硬件维修次数） 基线数据： 目标值：12月31日≥2000h 年度目标进度：实际值/目标值 | F6: 数字中台 （季明清） 维修单 （郭轶） | G6: / | H6: 2000 | I6: =K6/H6 -> 0.555 | J6: 570 | K6: 1110 | L6: =K6/J6 -> 1.9473684 | M6: =IF(L6>=1.5,80,IF(L6>=1,60+(L6-1)/0.5*20,IF(L6>=0.5,40+(L6-0.5)/0.5*20,L6/0.5*40))) -> 80
A7: MTPF提升专项 | B7: 徐融 | C7: Titan810 "1460"指标（小时） | D7: 徐融 | E7: 1460 = 设备运行总时长/（软件自恢复失败次数+硬件维修次数） 基线数据： 目标值：12月31日≥2000h 年度目标进度：实际值/目标值 | F7: 数字中台 （季明清） 维修单 （郭轶） | G7: / | H7: 2000 | I7: =K7/H7 -> 0.512 | J7: 570 | K7: 1024 | L7: =K7/J7 -> 1.7964912 | M7: =IF(L7>=1.5,80,IF(L7>=1,60+(L7-1)/0.5*20,IF(L7>=0.5,40+(L7-0.5)/0.5*20,L7/0.5*40))) -> 80
A8: 8H部署专项 | B8: 崔凯旋 | C8: SWGT 部署时长（小时） | D8: 崔凯旋 | E8: 从进场到完成部署的总耗时（小时） 基线数据：2025年全年平均值 目标值：8月31日前实现SW GT 8小时内完成机器部署 目标进度：目标值/实际值 | F8: 数字中台 （郭轶） | G8: 39.2 | H8: 8 | I8: =H8/K8 -> 0.34042553 | J8: 27 | K8: 23.5 | L8: =J8/K8 -> 1.1489362 | M8: =IF(L8>=1.5,80,IF(L8>=1,60+(L8-1)/0.5*20,IF(L8>=0.5,40+(L8-0.5)/0.5*20,L8/0.5*40))) -> 65.957447
A9: 8H部署专项 | B9: 崔凯旋 | C9: Titan810 部署时长（小时） | D9: 崔凯旋 | E9: 从进场到完成部署的总耗时（小时） 基线数据：2025年全年平均值 目标值：12月31日前实现Titan 810 8小时内完成机器部署 目标进度：目标值/实际值 | F9: 数字中台 （郭轶） | G9: 74.7 | H9: 8 | I9: =H9/K9 -> 0.15936255 | J9: 50 | K9: 50.2 | L9: =J9/K9 -> 0.99601594 | M9: =IF(L9>=1.5,80,IF(L9>=1,60+(L9-1)/0.5*20,IF(L9>=0.5,40+(L9-0.5)/0.5*20,L9/0.5*40))) -> 59.840637
A10: 数字中台专项 | B10: 季明清 | C10: MES上线 | D10: 季明清 | E10: 非量化指标，以系统上线（100%）节点为准 基线数据：不涉及 目标值：4月底前完成MES上线 月度完成率：上线：100%、未上线：无风险70%、有风险：40%；每提前一天+2% 目标进度：30%+30%+40% | F10: 评审报告 （公司级-季明清） | G10: 非量化指标 不涉及 | H10: 4月底前完成MES上线 | J10: — | M10: =IF(L10>=1.5,80,IF(L10>=1,60+(L10-1)/0.5*20,IF(L10>=0.5,40+(L10-0.5)/0.5*20,L10/0.5*40))) -> 0
A11: 数字中台专项 | B11: 季明清 | C11: 三流合一 | D11: 季明清 | E11: 非量化指标，以系统上线（100%）节点为准 基线数据：不涉及 目标值：6月底前支撑财务和供应链管理 月度完成率：上线：100%、未上线：无风险70%、有风险：40%；每提前一天+2% 目标进度：30%+30%+40% | F11: 评审报告 （公司级-季明清） | G11: 非量化指标 不涉及 | H11: 6月底前支撑财务和供应链管理 | J11: — | M11: =IF(L11>=1.5,80,IF(L11>=1,60+(L11-1)/0.5*20,IF(L11>=0.5,40+(L11-0.5)/0.5*20,L11/0.5*40))) -> 0
A12: 数字中台专项 | B12: 季明清 | C12: 0号员工上线 | D12: 季明清 | E12: 非量化指标，以系统上线（100%）节点为准 基线数据：不涉及 目标值：8月底前完成0号员工上线 月度完成率：上线：100%、未上线：无风险70%、有风险：40%；每提前一天+2% 目标进度：30%+30%+40% | F12: 评审报告 （公司级-季明清） | G12: 非量化指标 不涉及 | H12: 8月底前完成0号员工上线 | J12: — | M12: =IF(L12>=1.5,80,IF(L12>=1,60+(L12-1)/0.5*20,IF(L12>=0.5,40+(L12-0.5)/0.5*20,L12/0.5*40))) -> 0
A13: 质量提升专项 | B13: 吴赛 | C13: 合同质量-异常率 | D13: 张海滨 | E13: 合同异常率=异常合同数/签约合同总数 | F13: 财务提供 | H13: 合同异常率≤5% | J13: ≤5% | M13: =IF(L13>=1.5,80,IF(L13>=1,60+(L13-1)/0.5*20,IF(L13>=0.5,40+(L13-0.5)/0.5*20,L13/0.5*40))) -> 0
A14: 质量提升专项 | B14: 吴赛 | C14: 合同质量-非正常优惠率 | D14: 张海滨 | E14: 非正常优惠率=非正常优惠合同金额/合同总额 | F14: 财务提供 | H14: 非正常优惠合同比例≤10% | J14: ≤10% | M14: =IF(L14>=1.5,80,IF(L14>=1,60+(L14-1)/0.5*20,IF(L14>=0.5,40+(L14-0.5)/0.5*20,L14/0.5*40))) -> 0
A15: 质量提升专项 | B15: 吴赛 | C15: 研发质量-SWGT测试泄漏率 | D15: 袁德明 | E15: 测试泄漏率 = 现场问题总数 / (测试故障数+生产问题数+现场问题数)--不包含重复问题、非问题 基线数据：高于底线值40%不得分 目标值：截至12月31日所有数据 目标进度：（底线值-实际值）/(底线值-目标值) | F15: JIRA | G15: 0.4 | H15: 0.1 | I15: =(G15-K15)/(G15-H15) -> 0.24266667 | J15: 0.3 | K15: 0.3272 | L15: =(G15-K15)/(G15-J15) -> 0.728 | M15: =IF(L15>=1.5,80,IF(L15>=1,60+(L15-1)/0.5*20,IF(L15>=0.5,40+(L15-0.5)/0.5*20,L15/0.5*40))) -> 49.12
A16: 质量提升专项 | B16: 吴赛 | C16: 研发质量-Titan810测试泄漏率 | D16: 袁德明 | E16: 测试泄漏率 = 现场问题总数 / (测试故障数+生产问题数+现场问题数)--不包含重复问题、非问题 基线数据：高于底线值40%不得分 目标值：2025年开始截至2026年12月所有数据 目标进度：（底线值-实际值）/(底线值-目标值) | F16: JIRA | G16: 0.4 | H16: 0.1 | I16: =(G16-K16)/(G16-H16) -> 0.501 | J16: 0.3 | K16: 0.2497 | L16: =(G16-K16)/(G16-J16) -> 1.503 | M16: =IF(L16>=1.5,80,IF(L16>=1,60+(L16-1)/0.5*20,IF(L16>=0.5,40+(L16-0.5)/0.5*20,L16/0.5*40))) -> 80
A17: 质量提升专项 | B17: 吴赛 | C17: 研发质量-JIRA及时关闭率 | D17: 袁德明 | E17: JIRA现场问题/测试故障/生产问题中，30天内已关闭数/总数--历史解决+新增30天解决 基线数据：2026年Q1数据 目标值：2026年Q4数据 目标进度：（实际值-基线值）/(目标值-基线值) | F17: JIRA | G17: 0.4109 | H17: 0.9 | I17: =(K17-G17)/(H17-G17) -> 0.17419751 | J17: 0.6 | K17: 0.4961 | L17: =(K17-G17)/(J17-G17) -> 0.45055526 | M17: =IF(L17>=1.5,80,IF(L17>=1,60+(L17-1)/0.5*20,IF(L17>=0.5,40+(L17-0.5)/0.5*20,L17/0.5*40))) -> 36.044421
A18: 质量提升专项 | B18: 吴赛 | C18: 采购质量-来料批次不良 | D18: 巴路瑶 | E18: 每月来料检验中不良批次数量 基线数据：暂无 目标值：0 目标进度：按当月有无，判定0或100% | F18: 供应链提供 质量审核 （巴路瑶） | G18: 暂无 | H18: 来料批次不良0次 | I18: 1 | J18: 0次 | K18: 0 | L18: 1 | M18: =IF(L18>=1.5,80,IF(L18>=1,60+(L18-1)/0.5*20,IF(L18>=0.5,40+(L18-0.5)/0.5*20,L18/0.5*40))) -> 60
A19: 质量提升专项 | B19: 吴赛 | C19: 生产过程质量-SWGT 开箱合格率 | D19: 吴赛 | E19: 开箱合格率 = 开箱合格台数/总出货台数 基线数据：2025年全年80.6% 目标值：开箱合格率≥98%（10-12月） 目标进度：（实际值-基线值）/(目标值-基线值) | F19: 质量统计 （吴赛） | G19: 0.806 | H19: 0.98 | I19: =K19/H19 -> 0.51020408 | J19: 0.85 | K19: 0.5 | L19: =K19/J19 -> 0.58823529 | M19: =IF(L19>=1.5,80,IF(L19>=1,60+(L19-1)/0.5*20,IF(L19>=0.5,40+(L19-0.5)/0.5*20,L19/0.5*40))) -> 43.529412
A20: 质量提升专项 | B20: 吴赛 | C20: 生产过程质量-SW50 开箱合格率 | D20: 吴赛 | E20: 开箱合格率 = 开箱合格台数/总出货台数 基线数据：2025年全年80.42% 目标值：开箱合格率≥98%（10-12月） 目标进度：（实际值-基线值）/(目标值-基线值) | F20: 质量统计 （吴赛） | G20: 0.8042 | H20: 0.98 | I20: =K20/H20 -> 0.79367347 | J20: 0.85 | K20: 0.7778 | L20: =K20/J20 -> 0.91505882 | M20: =IF(L20>=1.5,80,IF(L20>=1,60+(L20-1)/0.5*20,IF(L20>=0.5,40+(L20-0.5)/0.5*20,L20/0.5*40))) -> 56.602353
A21: 质量提升专项 | B21: 吴赛 | C21: 生产过程质量-Titan810 开箱合格率 | D21: 吴赛 | E21: 开箱合格率 = 开箱合格台数/总出货台数 基线数据：2025年全年75% 目标值：开箱合格率≥98%（10-12月） 目标进度：（实际值-基线值）/(目标值-基线值) | F21: 质量统计 （吴赛） | G21: 0.75 | H21: 0.98 | I21: =K21/H21 -> 0 | J21: 0.85 | K21: 0 | L21: =K21/J21 -> 0 | M21: =IF(L21>=1.5,80,IF(L21>=1,60+(L21-1)/0.5*20,IF(L21>=0.5,40+(L21-0.5)/0.5*20,L21/0.5*40))) -> 0
A22: 质量提升专项 | B22: 吴赛 | C22: 生产过程质量-SWGT 90天内维修率 | D22: 吴赛 | E22: 90天内维修率 = 90天内发生维修的台数/总出货台数 基线数据：无 目标值：90天内维修率≤3%（10-12月） 目标进度：目标值/实际值 | F22: 质量统计 （吴赛） | G22: / | H22: 0.03 | I22: =H22/K22 -> 0.10500525 | J22: 0.07 | K22: 0.2857 | L22: =J22/K22 -> 0.24501225 | M22: =IF(L22>=1.5,80,IF(L22>=1,60+(L22-1)/0.5*20,IF(L22>=0.5,40+(L22-0.5)/0.5*20,L22/0.5*40))) -> 19.60098
A23: 质量提升专项 | B23: 吴赛 | C23: 生产过程质量-SW50 90天内维修率 | D23: 吴赛 | E23: 90天内维修率 = 90天内发生维修的台数/总出货台数 基线数据：无 目标值：90天内维修率≤3%（10-12月） 目标进度：目标值/实际值 | F23: 质量统计 （吴赛） | G23: / | H23: 0.03 | I23: =H23/K23 -> 0.17996401 | J23: 0.07 | K23: 0.1667 | L23: =J23/K23 -> 0.41991602 | M23: =IF(L23>=1.5,80,IF(L23>=1,60+(L23-1)/0.5*20,IF(L23>=0.5,40+(L23-0.5)/0.5*20,L23/0.5*40))) -> 33.593281
A24: 质量提升专项 | B24: 吴赛 | C24: 生产过程质量-Titan810 90天内维修率 | D24: 吴赛 | E24: 90天内维修率 = 90天内发生维修的台数/总出货台数 基线数据：无 目标值：90天内维修率≤3%（10-12月） 目标进度：目标值/实际值 | F24: 质量统计 （吴赛） | G24: / | H24: 0.03 | I24: =H24/K24 -> 0.12 | J24: 0.07 | K24: 0.25 | L24: =J24/K24 -> 0.28 | M24: =IF(L24>=1.5,80,IF(L24>=1,60+(L24-1)/0.5*20,IF(L24>=0.5,40+(L24-0.5)/0.5*20,L24/0.5*40))) -> 22.4
A25: 质量提升专项 | B25: 吴赛 | C25: 售后质量-问题一次性解决率 | D25: 崔凯旋 | E25: 售后问题一次解决数/解决总数 在系统未上线之前，数字中台中的售后维修流程统计（通过一台机器90天内的重复维修计算） 基线数据：待补充 目标值：≥95% 目标进度：实际值/目标值 | F25: 6月前手工 6月后系统 （郭轶） | G25: 需要基线值计算进度和月度目标达成率 | H25: 0.95 | J25: 0.85 | M25: =IF(L25>=1.5,80,IF(L25>=1,60+(L25-1)/0.5*20,IF(L25>=0.5,40+(L25-0.5)/0.5*20,L25/0.5*40))) -> 0
A26: 质量提升专项 | B26: 吴赛 | C26: 售后质量-平均解决时效（一线城市）（小时） | D26: 崔凯旋 | E26: 售后问题从提出到解决时间 在系统未上线之前，以维修工单的起止时间计算 基线数据：暂无 目标值：≤48H 目标进度：（基线值-实际值）/(基线值-目标值) | F26: 6月前手工 6月后系统 （郭轶） | G26: 需要基线值计算进度和月度目标达成率 | H26: 48 | J26: 72H | M26: =IF(L26>=1.5,80,IF(L26>=1,60+(L26-1)/0.5*20,IF(L26>=0.5,40+(L26-0.5)/0.5*20,L26/0.5*40))) -> 0
A27: 质量提升专项 | B27: 吴赛 | C27: 售后质量-平均解决时效（二线城市）（小时） | D27: 崔凯旋 | E27: 售后问题从提出到解决时间 在系统未上线之前，以维修工单的起止时间计算 基线数据：暂无 目标值：≤72H 目标进度：（基线值-实际值）/(基线值-目标值) | F27: 6月前手工 6月后系统 （郭轶） | G27: 需要基线值计算进度和月度目标达成率 | H27: 72 | J27: 120H | M27: =IF(L27>=1.5,80,IF(L27>=1,60+(L27-1)/0.5*20,IF(L27>=0.5,40+(L27-0.5)/0.5*20,L27/0.5*40))) -> 0
A28: 质量提升专项 | B28: 吴赛 | C28: 售后质量-平均解决时效（海外核心国家）（小时） | D28: 崔凯旋 | E28: 售后问题从提出到解决时间 在系统未上线之前，以维修工单的起止时间计算 基线数据：暂无 目标值：≤48H 目标进度：（基线值-实际值）/(基线值-目标值) | F28: 6月前手工 6月后系统 （郭轶） | G28: 需要基线值计算进度和月度目标达成率 | H28: 48 | J28: 120H | M28: =IF(L28>=1.5,80,IF(L28>=1,60+(L28-1)/0.5*20,IF(L28>=0.5,40+(L28-0.5)/0.5*20,L28/0.5*40))) -> 0
A29: 质量提升专项 | B29: 吴赛 | C29: 售后质量-平均解决时效（海外其他国家）（小时） | D29: 崔凯旋 | E29: 售后问题从提出到解决时间 在系统未上线之前，以维修工单的起止时间计算 基线数据：暂无 目标值：≤72H 目标进度：（基线值-实际值）/(基线值-目标值) | F29: 6月前手工 6月后系统 （郭轶） | G29: 需要基线值计算进度和月度目标达成率 | H29: 72 | J29: 120H | M29: =IF(L29>=1.5,80,IF(L29>=1,60+(L29-1)/0.5*20,IF(L29>=0.5,40+(L29-0.5)/0.5*20,L29/0.5*40))) -> 0
A30: 渠道管理能力提升 | B30: 张海滨 | C30: 经销商收入（累计） | D30: 张海滨 | E30: 各月经销商实际签约/交付收入累计额 | F30: 财务提供 | H30: 12月经销商累计收入1.6亿元 | J30: 1500万 | M30: =IF(L30>=1.5,80,IF(L30>=1,60+(L30-1)/0.5*20,IF(L30>=0.5,40+(L30-0.5)/0.5*20,L30/0.5*40))) -> 0
A31: 渠道管理能力提升 | B31: 张海滨 | C31: 新增经销商数量（月新增） | D31: 张海滨 | E31: 每月新签合作协议的经销商数量 | F31: 财务提供 | H31: 每月新增经销商3个 | J31: 新增3个 | M31: =IF(L31>=1.5,80,IF(L31>=1,60+(L31-1)/0.5*20,IF(L31>=0.5,40+(L31-0.5)/0.5*20,L31/0.5*40))) -> 0
A32: 渠道管理能力提升 | B32: 张海滨 | C32: 经销商存销比 | D32: 张海滨 | E32: 存销比 = 经销商库存 / 月销量 | F32: 财务提供 | H32: Q3起存销比≤1.5:1 | J32: 2:1 | M32: =IF(L32>=1.5,80,IF(L32>=1,60+(L32-1)/0.5*20,IF(L32>=0.5,40+(L32-0.5)/0.5*20,L32/0.5*40))) -> 0
A33: 渠道管理能力提升 | B33: 张海滨 | C33: 经销商复购率 | D33: 张海滨 | E33: 复购率 = 有复购行为的经销商数 / 存量经销商总数 | F33: 财务提供 | H33: 12月经销商复购率达70% | J33: 10% | M33: =IF(L33>=1.5,80,IF(L33>=1,60+(L33-1)/0.5*20,IF(L33>=0.5,40+(L33-0.5)/0.5*20,L33/0.5*40))) -> 0
A34: 渠道管理能力提升 | B34: 张海滨 | C34: 国内累计收费服务经销商占比超过35% | D34: 张海滨 | E34: 国内国际累计收费服务经销商比例占比超过35%
A35: 渠道管理能力提升 | B35: 张海滨 | C35: 国际累计收费服务经销商占比超过35% | D35: 张海滨
A36: Marketing能力提升 | B36: 张海滨 | C36: 毛利率 | D36: 张海滨 | E36: 毛利率 = (收入 - 成本) / 收入 | F36: 财务数据 | H36: 12月毛利率达60% | J36: 30% | M36: =IF(L36>=1.5,80,IF(L36>=1,60+(L36-1)/0.5*20,IF(L36>=0.5,40+(L36-0.5)/0.5*20,L36/0.5*40))) -> 0
A37: Marketing能力提升 | B37: 张海滨 | C37: 应收周转天数 | D37: 张海滨 | E37: 待定 | F37: 财务数据 | H37: 12月应收周转天数≤40天 | J37: 98天 | M37: =IF(L37>=1.5,80,IF(L37>=1,60+(L37-1)/0.5*20,IF(L37>=0.5,40+(L37-0.5)/0.5*20,L37/0.5*40))) -> 0
A38: 政府资金专项 | B38: 何波 | C38: 政府资金到账额（万元） | D38: 何波 | E38: 实际到账/减免金额累计 基线数据：0 目标值：到账1750万元（含减免费用）南京1000万，嘉兴750万 目标进度：实际值/目标值 | F38: 财务确认 | G38: 0 | H38: 1750 | J38: 到账300万 | M38: =IF(L38>=1.5,80,IF(L38>=1,60+(L38-1)/0.5*20,IF(L38>=0.5,40+(L38-0.5)/0.5*20,L38/0.5*40))) -> 0
A39: 政府资金专项 | B39: 何波 | C39: 新增政府资金获批（万元） | D39: 何波 | E39: 累计政府获批资金（补贴或减免） 基线数据：0 目标值：新增3000万获批，南京500万，嘉兴1500万，深圳1000万 目标进度：实际值/目标值 | F39: 政府批示文件 | G39: 0 | H39: 3000 | J39: — | M39: =IF(L39>=1.5,80,IF(L39>=1,60+(L39-1)/0.5*20,IF(L39>=0.5,40+(L39-0.5)/0.5*20,L39/0.5*40))) -> 0
A40: 降本专项 | B40: 巴路瑶 | C40: GT非独家物料占比 | D40: 陈栋力 | E40: GT非独家物料金额 / GT物料总额 基线数据：以2026年2月为基线 目标值：6月底GT非独家占比达到85% 目标进度：实际值/目标值 | F40: 质量统计 以BOM为准 | G40: 0.12 | H40: 0.85 | I40: =K40/H40 -> 0.27411765 | J40: 0.3 | K40: 0.233 | L40: =K40/J40 -> 0.77666667 | M40: =IF(L40>=1.5,80,IF(L40>=1,60+(L40-1)/0.5*20,IF(L40>=0.5,40+(L40-0.5)/0.5*20,L40/0.5*40))) -> 51.066667
A41: 降本专项 | B41: 巴路瑶 | C41: T810非独家物料占比 | D41: 陈栋力 | E41: T810非独家物料金额 / T810物料总额 基线数据：以2026年2月为基线 目标值：6月底T810非独家占比达到65% 目标进度：实际值/目标值 | F41: 质量统计 以BOM为准 | G41: 0.23 | H41: 0.65 | I41: =K41/H41 -> 0.38476923 | J41: 0.25 | K41: 0.2501 | L41: =K41/J41 -> 1.0004 | M41: =IF(L41>=1.5,80,IF(L41>=1,60+(L41-1)/0.5*20,IF(L41>=0.5,40+(L41-0.5)/0.5*20,L41/0.5*40))) -> 60.016
A42: 降本专项 | B42: 巴路瑶 | C42: GT BOM成本降低（元） | D42: 巴路瑶 | E42: 采购成本降低额（含税，相对基准BOM） 基线数据：以2025年12月为基线 目标值：10000元（含税），6月前采购额，7月后发货额 目标进度：实际值/目标值 | F42: 生产提供（巴路瑶），财务核实（袁子清） | G42: 0 | H42: 10000 | I42: =K42/H42 -> 0.209043 | J42: 1454 | K42: 2090.43 | L42: =K42/J42 -> 1.4377098 | M42: =IF(L42>=1.5,80,IF(L42>=1,60+(L42-1)/0.5*20,IF(L42>=0.5,40+(L42-0.5)/0.5*20,L42/0.5*40))) -> 77.508391
A43: 降本专项 | B43: 巴路瑶 | C43: GT包装成本降低（元） | D43: 巴路瑶 | E43: 包装成本降低额（元/套），相对现有包装成本 基线数据：以2025年12月为基线 目标值：330元，6月前采购额，7月后发货额 目标进度：实际值/目标值 | F43: 生产提供（巴路瑶），财务核实（袁子清） | G43: 0 | H43: 330 | I43: =K43/H43 -> 0.32424242 | J43: 330 | K43: 107 | L43: =K43/J43 -> 0.32424242 | M43: =IF(L43>=1.5,80,IF(L43>=1,60+(L43-1)/0.5*20,IF(L43>=0.5,40+(L43-0.5)/0.5*20,L43/0.5*40))) -> 25.939394
A44: 降本专项 | B44: 巴路瑶 | C44: 810 BOM成本降低（元） | D44: 巴路瑶 | E44: 采购成本降低额（含税，相对基准BOM） 基线数据：以2025年12月为基线 目标值：30000元（含税），6月前采购额，7月后发货额 目标进度：实际值/目标值 | F44: 生产提供（巴路瑶），财务核实（袁子清） | G44: 0 | H44: 30000 | I44: =K44/H44 -> 0.038070667 | J44: 1351 | K44: 1142.12 | L44: =K44/J44 -> 0.8453886 | M44: =IF(L44>=1.5,80,IF(L44>=1,60+(L44-1)/0.5*20,IF(L44>=0.5,40+(L44-0.5)/0.5*20,L44/0.5*40))) -> 53.815544
A45: 降本专项 | B45: 巴路瑶 | C45: 810包装成本降低（元） | D45: 巴路瑶 | E45: 包装成本降低额（元/套），相对现有包装成本 基线数据：以2025年12月为基线 目标值：707元，6月前采购额，7月后发货额 目标进度：实际值/目标值 | F45: 生产提供（巴路瑶），财务核实（袁子清） | G45: 0 | H45: 707 | I45: =K45/H45 -> 0.21173975 | J45: 707 | K45: 149.7 | L45: =K45/J45 -> 0.21173975 | M45: =IF(L45>=1.5,80,IF(L45>=1,60+(L45-1)/0.5*20,IF(L45>=0.5,40+(L45-0.5)/0.5*20,L45/0.5*40))) -> 16.93918
A46: 生产提效降费专项 | B46: 夏文昊 | C46: 全年生产成本占比 | D46: 夏文昊 | E46: 生产成本（人工/固定资产折旧/水电）/发货成本 基线数据：以2025年度为基线（不包括水电费） 目标值：全年生产成本占比不高于6% 目标进度：目标值/实际值 | F46: 财务数据 （袁子清） | G46: 0.1224 | H46: 0.06 | I46: =H46/K46 -> 0.30659172 | J46: 0.1 | K46: 0.1957 | L46: =J46/K46 -> 0.5109862 | M46: =IF(L46>=1.5,80,IF(L46>=1,60+(L46-1)/0.5*20,IF(L46>=0.5,40+(L46-0.5)/0.5*20,L46/0.5*40))) -> 40.439448
A47: 库存周转专项 | B47: 张珂铜 | C47: 库存周转天数 | D47: 张珂铜 | E47: 3、4、5缺少月度目标 周期初、末总成本均值为A，周期内发货成本B 库存周转天数=周期天数/（B/A） 基线数据：以2026年3月为基线 目标值：全年库存周转天数达到55天（12月） 目标进度：目标值/实际值 | F47: 财务数据 （袁子清） | G47: 348 | H47: 55 | I47: =H47/K47 -> 0.15804598 | J47: — | K47: 348 | M47: =IF(L47>=1.5,80,IF(L47>=1,60+(L47-1)/0.5*20,IF(L47>=0.5,40+(L47-0.5)/0.5*20,L47/0.5*40))) -> 0
A48: 库存周转专项 | B48: 张珂铜 | C48: SWGT发货预测准确率-1周 | D48: 崔凯旋 | E48: min(当周发货数/预测数,当周预测数/发货数 基线数据：20%（本周） 目标值：1周预测准确率100%（左右浮动5%） 目标进度：（实际值-基线值）/(目标值-基线值) | F48: 运营管理部 (徐萍提供 崔凯旋审核) | G48: 暂无 | H48: 1 | J48: 1 | K48: 0.2 | L48: =K48/J48 -> 0.2 | M48: =IF(L48>=1.5,80,IF(L48>=1,60+(L48-1)/0.5*20,IF(L48>=0.5,40+(L48-0.5)/0.5*20,L48/0.5*40))) -> 16
A49: 库存周转专项 | B49: 张珂铜 | C49: SW50发货预测准确率-1周 | D49: 崔凯旋 | E49: 当周发货数/预测数 基线数据：20%（本周） 目标值：1周预测准确率100%（左右浮动5%） 目标进度：（实际值-基线值）/(目标值-基线值) | F49: 运营管理部 (徐萍提供 崔凯旋审核) | G49: 暂无 | H49: 1 | J49: 1 | K49: 0.2 | L49: =K49/J49 -> 0.2 | M49: =IF(L49>=1.5,80,IF(L49>=1,60+(L49-1)/0.5*20,IF(L49>=0.5,40+(L49-0.5)/0.5*20,L49/0.5*40))) -> 16
A50: 库存周转专项 | B50: 张珂铜 | C50: Titan810发货预测准确率-1周 | D50: 崔凯旋 | E50: 当周发货数/预测数 基线数据：20%（本周） 目标值：1周预测准确率100%（左右浮动5%） 目标进度：（实际值-基线值）/(目标值-基线值) | F50: 运营管理部 (徐萍提供 崔凯旋审核) | G50: 暂无 | H50: 1 | J50: 1 | K50: 0.2 | L50: =K50/J50 -> 0.2 | M50: =IF(L50>=1.5,80,IF(L50>=1,60+(L50-1)/0.5*20,IF(L50>=0.5,40+(L50-0.5)/0.5*20,L50/0.5*40))) -> 16
A51: 库存周转专项 | B51: 张珂铜 | C51: SWGT发货预测准确率-4周 | D51: 崔凯旋 | E51: 4周滚动预测准确率---没有4周？ 基线数据：暂无 目标值：4周预测准确率≥85% 目标进度：（实际值-基线值）/(目标值-基线值) | F51: 运营管理部 (徐萍提供 崔凯旋审核) | G51: 暂无 | H51: 0.85 | J51: 0.8 | L51: =K51/J51 -> 0 | M51: =IF(L51>=1.5,80,IF(L51>=1,60+(L51-1)/0.5*20,IF(L51>=0.5,40+(L51-0.5)/0.5*20,L51/0.5*40))) -> 0
A52: 库存周转专项 | B52: 张珂铜 | C52: SW50发货预测准确率-4周 | D52: 崔凯旋 | E52: 4周滚动预测准确率---没有4周？ 基线数据：暂无 目标值：4周预测准确率≥85% 目标进度：（实际值-基线值）/(目标值-基线值) | F52: 运营管理部 (徐萍提供 崔凯旋审核) | G52: 暂无 | H52: 0.85 | J52: 0.8 | L52: =K52/J52 -> 0 | M52: =IF(L52>=1.5,80,IF(L52>=1,60+(L52-1)/0.5*20,IF(L52>=0.5,40+(L52-0.5)/0.5*20,L52/0.5*40))) -> 0
A53: 库存周转专项 | B53: 张珂铜 | C53: Titan810发货预测准确率-4周 | D53: 崔凯旋 | E53: 4周滚动预测准确率---没有4周？ 基线数据：暂无 目标值：4周预测准确率≥85% 目标进度：（实际值-基线值）/(目标值-基线值) | F53: 运营管理部 (徐萍提供 崔凯旋审核) | G53: 暂无 | H53: 0.85 | J53: 0.8 | L53: =K53/J53 -> 0 | M53: =IF(L53>=1.5,80,IF(L53>=1,60+(L53-1)/0.5*20,IF(L53>=0.5,40+(L53-0.5)/0.5*20,L53/0.5*40))) -> 0
A54: 库存周转专项 | B54: 张珂铜 | C54: SWGT发货预测准确率-5周 | D54: 崔凯旋 | E54: 5周滚动预测准确率--暂无数据 基线数据：暂无 目标值：5周预测准确率≥70% 目标进度：（实际值-基线值）/(目标值-基线值) | F54: 运营管理部 (徐萍提供 崔凯旋审核) | G54: 暂无 | H54: 0.7 | J54: 0.65 | L54: =K54/J54 -> 0 | M54: =IF(L54>=1.5,80,IF(L54>=1,60+(L54-1)/0.5*20,IF(L54>=0.5,40+(L54-0.5)/0.5*20,L54/0.5*40))) -> 0
A55: 库存周转专项 | B55: 张珂铜 | C55: SW50发货预测准确率-5周 | D55: 崔凯旋 | E55: 5周滚动预测准确率--暂无数据 基线数据：暂无 目标值：5周预测准确率≥70% 目标进度：（实际值-基线值）/(目标值-基线值) | F55: 运营管理部 (徐萍提供 崔凯旋审核) | G55: 暂无 | H55: 0.7 | J55: 0.65 | L55: =K55/J55 -> 0 | M55: =IF(L55>=1.5,80,IF(L55>=1,60+(L55-1)/0.5*20,IF(L55>=0.5,40+(L55-0.5)/0.5*20,L55/0.5*40))) -> 0
A56: 库存周转专项 | B56: 张珂铜 | C56: Titan810发货预测准确率-5周 | D56: 崔凯旋 | E56: 5周滚动预测准确率--暂无数据 基线数据：暂无 目标值：5周预测准确率≥70% 目标进度：（实际值-基线值）/(目标值-基线值) | F56: 运营管理部 (徐萍提供 崔凯旋审核) | G56: 暂无 | H56: 0.7 | J56: 0.65 | L56: =K56/J56 -> 0 | M56: =IF(L56>=1.5,80,IF(L56>=1,60+(L56-1)/0.5*20,IF(L56>=0.5,40+(L56-0.5)/0.5*20,L56/0.5*40))) -> 0
A57: 预算管理能力提升专项 | B57: 袭丽丽 | C57: 主营业务经营性现金流 | D57: 袭丽丽 | E57: 主营业务经营性现金流净额（财务报表数据） 基线数据：暂无 目标值：主营业务经营性现金流为正 目标进度：（实际值-基线值）/(目标值-基线值) | F57: 财务数据 | H57: 0 | J57: -223.16 | M57: =IF(L57>=1.5,80,IF(L57>=1,60+(L57-1)/0.5*20,IF(L57>=0.5,40+(L57-0.5)/0.5*20,L57/0.5*40))) -> 0
A58: 核算能力提升专项 | B58: 袭丽丽 | C58: 财务报表出具时效 | D58: 袭丽丽 | E58: 每月出具财务报表的天数 基线数据：不涉及 目标值：系统上线前每月13日前出报表，系统上线后每月7日前出财务报表 目标进度&每月完成率：达成100分，每推迟一天扣25分 | F58: 财务总监反馈 领导核实 | H58: 系统上线前每月13日前出报表，系统上线后每月7日前出财务报表 | J58: 协调台账建立，出报表预测 | M58: =IF(L58>=1.5,80,IF(L58>=1,60+(L58-1)/0.5*20,IF(L58>=0.5,40+(L58-0.5)/0.5*20,L58/0.5*40))) -> 0
A59: 人力提效专项 | B59: 杨帆 | C59: 万元人力成本收入 | D59: 杨帆 | E59: 万元人力成本收入 = 营业收入/人力资源成本 基线数据：暂无 目标值：每1万元人力资源成本带来3万元收入 目标进度：（实际值-基线值）/(目标值-基线值) 无月度目标值 | F59: 财务数据 | J59: 高密度人才到岗、考核方案确定 | M59: =IF(L59>=1.5,80,IF(L59>=1,60+(L59-1)/0.5*20,IF(L59>=0.5,40+(L59-0.5)/0.5*20,L59/0.5*40))) -> 0
A60: 人力降费专项 | B60: 杨帆 | C60: 人力相关费用节约 | D60: 杨帆 | E60: 劳务服务费+猎头费+招聘费实际支出对比上年降低额 基线数据：0 目标值：降低46万元 月度完成率：以里程碑活动计，完成且开始降费得100分；完成但未降费，未完成但降费得70分；未完成且未降费得40分。 目标进度：实际值/基线值 | F60: 财务数据 | J60: — | M60: =IF(L60>=1.5,80,IF(L60>=1,60+(L60-1)/0.5*20,IF(L60>=0.5,40+(L60-0.5)/0.5*20,L60/0.5*40))) -> 0

Sheet 绩效应用
A1: 专项名称 | B1: 子专项 | C1: 奖金总额（万元） | D1: 项目成员 | E1: 绩效应用方案 | F1: 个人奖金分配规则 | G1: 4月应用 | H1: 5月应用 | I1: 6月应用 | J1: 7月应用 | K1: 8月应用 | L1: 9月应用 | M1: 10月应用 | N1: 11月应用 | O1: 12月应用
A2: MTPF提升专项 | C2: 12 | D2: 骨干成员： 徐融、赵鹏飞、巴路遥、夏文昊、崔凯旋 团队成员： 杨儡、季明清、陈晨光、徐倩楠、卢伟、戴程、张贵禹 | E2: 1、考核规则： MTPF权重占比50%，1460权重占比50%； 达成得满分，未达成得0分； 2、奖励规则： 过程奖金占40%，根据里程碑平均安排，里程碑达成即奖励；月度未达成：月度绩效考核体现 项目总目标占60%，年达成总目标，团队成员发放一次性奖金，未达成不予发放； | G2: 待提报 | H2: 待提报 | I2: 待提报 | J2: 待提报 | K2: 待提报 | L2: 待提报 | M2: 待提报 | N2: 待提报 | O2: 待提报
A3: 8H部署专项 | C3: 15 | D3: 骨干成员： 崔凯旋、赖禹诚、胡剑锋、徐融、赵鹏飞、季明清、陈晨光 团队成员： 张晨光、郭轶、卢伟、王家轩、王江玉、葛毓琴、孙威威、史博文 | E3: 1、考核细则： SW 50权重60%；Titan810权重40%；目标达成得满分，目标未达成得0分；月度得分=产品权重*产品目标得分； 2、奖励细则： （1）过程激励额度占40%，按里程碑节点个数平均分布；里程碑达成即奖励，未达成不激励 （2）年度目标额度占60%；年度目标达成，即奖励，未达成不激励 | F3: 月度激励部分：骨干占40%，团队成员占60%；骨干成员和团队成员平均分配；年度激励部分：骨干占60%；团队成员占40%；骨干成员和团队成员平均分配 | G3: 待提报 | H3: 待提报 | I3: 待提报 | J3: 待提报 | K3: 待提报 | L3: 待提报 | M3: 待提报 | N3: 待提报 | O3: 待提报
A4: 数字中台专项 | C4: 10 | D4: 骨干成员： 季明清、袭丽丽、刘欣仪、张海滨、夏文昊、张珂铜 团队成员： 莫严、羊柬衡、刘佳慧、吴琳、袁子清、陈雨秋、季阳阳 | E4: 考核细则： 1、Mes4月按时上线，即奖励；未达成，不奖励（2） 2、三流合一6月按时达成，即奖励；未达成，不奖励（6） 3、零号员工8月按时上线，达成即奖励，未达成，不奖励（2） | G4: 待提报 | H4: / | I4: 待提报 | J4: / | K4: 待提报 | M4: / | N4: / | O4: /
A5: 质量提升专项 | B5: 合同质量提升 | C5: 1 | D5: 张海滨、袭丽丽、崔凯旋、徐萍 | E5: 1、考核规则 两项内容各占50%权重，按照实际完成目标线性得分，低于目标值15%以上不得分，得分70分为处罚线，85分为奖励线。每月进行目标完成统计，年度得分为12个月的平均分。 | F5: 平均分配，由项目管理委员会最后审定
B6: 研发质量提升 | C6: 5 | D6: 赵鹏飞，袁德明，陈晨光，季明清，冯景，宋丰懿，巴路瑶，张晨光，杨德鑫，吴赛 | E6: 两个指标，上半年目标全部达成，不扣钱，达成一个，扣5000，都不达成，扣10000；均摊到7到12月绩效；年底，全部达成，奖金池全额发放（对冲上半年扣除部分）；达成一个，发20000；都不达成，不发放。 | F6: 平均分配，由项目管理委员会最后审定
B7: 采购质量提升 | C7: 2 | D7: 谷万成、巴路遥、夏文昊、曹阳 | E7: 当月出现批次不合格，对应采购人处罚500元；全年未出现批次不合格的一次性奖励5000元 | F7: 平均分配
B8: 生产过程质量提升 | C8: 8 | D8: 骨干成员： 赖禹诚、胡剑烽、宋丰懿、冯景、巴路遥、夏文昊、吴赛 团队成员： 吴赛、袁德明、朱尚荣、仲王磊、王昕珏、任静、罗文选、高文豪、张洪意、王旭忠、曹长业 | E8: 1、奖励规则： 过程奖金占40%，根据里程碑平均安排，里程碑达成即奖励；月度未达成：月度绩效考核体现；重大质量问题按照质量问责管理制度执行 项目总目标占60%，年达成总目标，团队成员发放一次性奖金，未达成不予发放； 2、考核规则 3月至6月加权计算得分低于75%为未达成； 7月至12月加权计算得分低于80%为未达成； 开箱合格率达成率：（实际合格率 ÷ 当月目标合格率）； 维修率达成率：（当月目标合格率 ÷实际合格率 ）； 当月达成率=开箱合格率达成率*50%+维修率达成率*50% | F8: 平均分配
B9: 售后质量提升 | C9: 1 | D9: 郭轶，赵俊 | E9: 1、两个指标权重各50% 2、过程激励额度40%；年度目标额度60%； 季度考核细则：目标达成得满分，目标未达成得0分；月度得分=指标权重*目标得分； 年度奖励细则：两个指标目标全部达成，激励生效
A10: 渠道管理能力提升 | C10: 3 | D10: 张海滨、王志敏、范军、单辉宇、胡斌 | E10: 1、考核规则 收入权重30%，新增经销商权重20%、经销商存销比权重30%、经销商复购率权重20% 得分=单项权重*单项得分、得分≤60分，视为未达成，将进行处罚，处罚金额总额1.5万； 得分≥100分，视为达成，进行奖励。 2、奖励规则 过程奖金占40%，根据里程碑平均安排，里程碑达成即奖励；月度未达成：月度绩效考核体现；并进行对应奖励金额50%的处罚。 项目总目标占60%，年达成总目标，团队成员发放一次性奖金，未达成不予发放；并进行对应奖励金额50%的处罚。 达成即奖励，未达成进行处罚 | F10: 销售部门按照各自部门的完成准确率执行。销售管理部门和运营部门按照公司整体结果应用。结果按照季度进行应用
D11: 崔凯旋、张海滨、徐融、胡剑烽、赖禹城、王志敏、范军、单辉宇、胡斌 | E11: 1、考核规则 国际权重70%，国内30% 得分=单项权重*单项得分、得分≤60分，视为未达成，将进行处罚，处罚金额总额1.5万； 得分≥100分，视为达成，进行奖励。 2、奖励规则 过程奖金占40%，根据里程碑平均安排，里程碑达成即奖励；月度未达成：月度绩效考核体现；并进行对应奖励金额50%的处罚。 项目总目标占60%，年达成总目标，团队成员发放一次性奖金，未达成不予发放；并进行对应奖励金额50%的处罚。 达成即奖励，未达成进行处罚
A12: Marketing能力提升 | C12: 2 | D12: 张海滨、崔凯旋、王志敏、范军、单辉宇、胡斌 张珂铜 | E12: 1、考核规则 毛利率指标权重50%，应收周转天数指标权重50% 得分=单项权重*单项得分、得分≤60分，视为未达成，将进行处罚，处罚金额总额1万； 得分≥100分，视为达成，进行奖励。奖励总额2万 2、奖励规则 过程奖金占40%，根据里程碑平均安排，里程碑达成即奖励；月度未达成：月度绩效考核体现；并进行对应奖励金额50%的处罚。 项目总目标占60%，年达成总目标，团队成员发放一次性奖金，未达成不予发放；并进行对应奖励金额50%的处罚。 达成即奖励，未达成进行处罚 | F12: 销售部门按照各自部门的完成准确率执行。销售管理部门和运营部门按照公司整体结果应用。结果按照季度进行应用
A13: 政府资金专项 | C13: 5 | E13: （1）按此时间节点执行，政府资金按时到账或减免，责任团队可获5%的现金奖励，次月体现，由项目经理具体分配； （2）若当月未按时达成目标，按未完成比例减扣当月绩效。 （3）若月度目标延期但全年目标全部达成，需在年底将月度扣减绩效补回。 （4）项目运作过程中所需公司其他部门提供支持的，其他部门不提供或未及时提供支持的，导致项目未按时完成目标，由该部门负责人及分管领导承担相应罚则。 | F13: 项目经理分配
A14: 降本专项 | B14: 消除独家专项-GT | C14: 6 | D14: GT团队：陈栋力、巴路遥、莫严、曹阳、赵鹏飞、袁子清、胡剑烽、宁京冀、王昕珏、葛宏晨、孟阳、马壮、袁德明、刘欣仪、张珂铜、谷万成、吴思锐、万登源、夏文昊、宋丰懿、高文豪、张晨光、陈晨光、季明清； Titan810团队：陈栋力、巴路遥、莫严、曹阳、赵鹏飞、袁子清、赖禹诚、任静、王昕珏、罗文选、马壮、叶银、袁德明、刘欣仪、张珂铜、谷万成、吴思锐、万登源、夏文昊、张晨光、陈晨光、季明清； | E14: 过程奖金占40%，根据里程碑平均安排，里程碑达成即奖励；月度未达成：月度绩效考核体现 项目总目标占60%，年达成总目标，团队成员发放一次性奖金，未达成不予发放；
B15: 消除独家专项-810 | C15: 6 | E15: 过程奖金占40%，根据里程碑平均安排，里程碑达成即奖励；月度未达成：月度绩效考核体现 项目总目标占60%，年达成总目标，团队成员发放一次性奖金，未达成不予发放；
B16: SW降本专项 | C16: 50 | E16: 每月降本额度： ∑(某版本上月降本幅度/台×该版本本月发货量) 每月降本缺额： ∑(（1万元-某版本上月降本幅度/台）×该版本本月发货量) 目标完成率：每月降本额度/（1万元×本月发货量） 完成度小于90% 惩罚＝每月降本缺额× 1% 完成度大于等于90% 奖励 =每月降本额度× 3% 完成度大于100% 基础奖励全额发放，并可对超额部分额外提奖（3%） | F16: 暂定平均
B17: 810降本专项 | C17: 75 | E17: 每月降本额度： ∑(某版本上月降本幅度/台×该版本本月发货量) 每月降本缺额： ∑(（3万元-某版本上月降本幅度/台）×该版本本月发货量) 目标完成率：每月降本额度/（3万元×本月发货量） 完成度小于90% 惩罚＝每月降本缺额× 1% 完成度大于等于90% 奖励 =每月降本额度× 3% 完成度大于100% 基础奖励全额发放，并可对超额部分额外提奖（3%） | F17: 暂定平均
A18: 生产提效降费专项 | C18: 3 | D18: 生产部（夏文昊）、仓储物流部（张珂铜、吴思锐）、计划部（刘欣仪、万登源）、质检部（巴路瑶）、质量部（吴赛、袁德明）、研发部（徐融）、IT部（季明清）、工艺装备部（方哲）、采购部（谷万成）、售后部（崔凯旋）、销售部（张海滨）、三结合部（曹阳） | E18: 从达成6%的当月开始按当月机器发货量价格发放奖金，直至12月。发放比例为当月发货数*（12.24%-6%）*5% 超额贡献奖：成本低于6%，额外给予6%-x%降幅比例结合发货台数总金额的5%计算奖励，达到目标之时当月开始奖励。当月发货数*（6%-x%）*5% 11月底若没达到，12月份开始扣当月绩效，按x%-6%的差额结合年度发货台数的1%扣除。直到6%达成，若一月份没达成则按照当月发货计算处罚。 | F18: 平均分配
A19: 库存周转专项 | B19: 库存周转 | C19: 20 | D19: 供应链：张珂铜、刘欣仪、夏文昊、谷万成、巴路瑶、万登源、曹阳、吴思锐 市场：张海滨、王志敏、范军、单辉宇、胡斌 售后：崔凯旋、朱尚荣 IT：季明清、羊柬衡 | E19: 按照每个月度目标达成情况给予奖励或惩处 挑战目标达成则对应季度奖励金额*1.2 其中： 1.借货仓，每人不超过2套，借货金额占比不超过总库存18%，国内周转天数不超过30天，国外周转天数不超过100天（含物流周转）； 2.售后仓含wd售后备件，金额占比不超过总库存7%，周转天数不超过100天（含物流周转） 3.剩余的为原料仓和在线以及成品，按照上述两个仓的周转天数，要达到整体55天，原料仓和在线以及成品的整体周转要在45天之内 每月各团队负责人汇总评估当月达成情况，根据组内成员具体任务达成确定奖惩分配 | F19: 各团对负责人按月度团队分配总金额，分配到个人
B20: 预测准确率 | C20: 5 | D20: 张海滨 崔凯旋、王志敏、范军、单辉宇、胡斌，徐萍 | E20: 1、考核规则 一周预测准确率权重40%，4周准确率权重30%，5周准确率30%； 得分=单项权重*单项得分、得分≤60分，视为未达成，将进行处罚，处罚金额总额2.5万； 得分≥100分，视为达成，进行奖励。奖励总额5万； 2、奖励规则 过程奖金占40%，根据里程碑平均安排，里程碑达成即奖励；月度未达成：月度绩效考核体现；并进行对应奖励金额50%的处罚。 项目总目标占60%，年达成总目标，团队成员发放一次性奖金，未达成不予发放；并进行对应奖励金额50%的处罚。 达成即奖励，未达成进行处罚 | F20: 销售部门按照各自部门的预测准确率执行。销售管理部门和运营部门按照公司整体结果应用
A21: 预算管理能力提升专项 | C21: 5 | D21: 袭丽丽、吴琳、袁子清陈雨 秋、刘欣仪、张珂铜、张海 滨、徐萍、数字中台代表 | E21: 达成即奖励，团队成员发放一次性奖金； 未达成，月度绩效考核体现；
A22: 核算能力提升专项 | C22: 5 | D22: 袭丽丽、吴琳、袁子清、张 海滨、徐萍、崔凯旋、张珂铜、刘欣仪、徐融、人事代表、数字中台代表 | E22: 达成即奖励，团队成员发放一次性奖金； 未达成，月度绩效考核体现；
A23: 人力提效专项 | C23: 5 | D23: 钱飞飞、李蒙 | E23: 达成即奖励，团队成员发放一次性奖金； 未达成，月度绩效考核体现；
A24: 人力降费专项 | C24: 1 | D24: 孙林海、何波、李蒙、钱飞飞 | E24: 达成即奖励，团队成员发放一次性奖金； 未达成，月度绩效考核体现；
